{
"meta":{"test_sets":[],"test_metrics":[],"learn_metrics":[{"best_value":"Min","name":"RMSE"}],"launch_mode":"Train","parameters":"","iteration_count":1000,"learn_sets":["learn"],"name":"experiment"},
"iterations":[
{"learn":[0.9842347776],"iteration":0,"passed_time":0.1522382611,"remaining_time":152.0860229},
{"learn":[0.9704855828],"iteration":1,"passed_time":0.159924507,"remaining_time":79.80232899},
{"learn":[0.9584608272],"iteration":2,"passed_time":0.1675998352,"remaining_time":55.69901189},
{"learn":[0.9478393182],"iteration":3,"passed_time":0.1800486148,"remaining_time":44.8321051},
{"learn":[0.9386988787],"iteration":4,"passed_time":0.1913283102,"remaining_time":38.07433374},
{"learn":[0.9306723666],"iteration":5,"passed_time":0.2049411829,"remaining_time":33.95192263},
{"learn":[0.9235372775],"iteration":6,"passed_time":0.2159514451,"remaining_time":30.63425499},
{"learn":[0.9172761329],"iteration":7,"passed_time":0.2263294727,"remaining_time":28.06485461},
{"learn":[0.9119394523],"iteration":8,"passed_time":0.2382107894,"remaining_time":26.2296547},
{"learn":[0.9073344419],"iteration":9,"passed_time":0.2449380533,"remaining_time":24.24886727},
{"learn":[0.9033345374],"iteration":10,"passed_time":0.2543820407,"remaining_time":22.87125802},
{"learn":[0.8997263804],"iteration":11,"passed_time":0.2654016076,"remaining_time":21.85139902},
{"learn":[0.8966727849],"iteration":12,"passed_time":0.2761382834,"remaining_time":20.96526813},
{"learn":[0.894040577],"iteration":13,"passed_time":0.2891065062,"remaining_time":20.36135822},
{"learn":[0.8917558908],"iteration":14,"passed_time":0.3038386764,"remaining_time":19.95207308},
{"learn":[0.8896597078],"iteration":15,"passed_time":0.3173798016,"remaining_time":19.5188578},
{"learn":[0.8879596318],"iteration":16,"passed_time":0.3242067519,"remaining_time":18.74677865},
{"learn":[0.8864877761],"iteration":17,"passed_time":0.3356390053,"remaining_time":18.3109724},
{"learn":[0.8852028643],"iteration":18,"passed_time":0.3549158548,"remaining_time":18.32486598},
{"learn":[0.883999467],"iteration":19,"passed_time":0.3802884871,"remaining_time":18.63413587},
{"learn":[0.8830016935],"iteration":20,"passed_time":0.4025361353,"remaining_time":18.76585126},
{"learn":[0.8820662141],"iteration":21,"passed_time":0.4225363292,"remaining_time":18.78366045},
{"learn":[0.8812838071],"iteration":22,"passed_time":0.4438321761,"remaining_time":18.85321896},
{"learn":[0.8805562237],"iteration":23,"passed_time":0.4672181888,"remaining_time":19.00020634},
{"learn":[0.8799626003],"iteration":24,"passed_time":0.4823333179,"remaining_time":18.8109994},
{"learn":[0.8794934181],"iteration":25,"passed_time":0.5072429322,"remaining_time":19.00210061},
{"learn":[0.8790493279],"iteration":26,"passed_time":0.527697066,"remaining_time":19.01663871},
{"learn":[0.8786668941],"iteration":27,"passed_time":0.5582007911,"remaining_time":19.37754175},
{"learn":[0.8782674083],"iteration":28,"passed_time":0.5923361027,"remaining_time":19.83304675},
{"learn":[0.8779706107],"iteration":29,"passed_time":0.6290163291,"remaining_time":20.33819464},
{"learn":[0.8776828126],"iteration":30,"passed_time":0.6469098351,"remaining_time":20.22114936},
{"learn":[0.8774323475],"iteration":31,"passed_time":0.6814832502,"remaining_time":20.61486832},
{"learn":[0.877198948],"iteration":32,"passed_time":0.6987021843,"remaining_time":20.47409128},
{"learn":[0.8769900251],"iteration":33,"passed_time":0.7128290241,"remaining_time":20.25273051},
{"learn":[0.8767879895],"iteration":34,"passed_time":0.7281134155,"remaining_time":20.07512703},
{"learn":[0.8766109453],"iteration":35,"passed_time":0.7415662505,"remaining_time":19.85749626},
{"learn":[0.8764777676],"iteration":36,"passed_time":0.7628848422,"remaining_time":19.85562441},
{"learn":[0.8763145366],"iteration":37,"passed_time":0.7859213894,"remaining_time":19.89622044},
{"learn":[0.8762099877],"iteration":38,"passed_time":0.7957634845,"remaining_time":19.60842843},
{"learn":[0.876103557],"iteration":39,"passed_time":0.8088235896,"remaining_time":19.41176615},
{"learn":[0.8759904127],"iteration":40,"passed_time":0.8212389092,"remaining_time":19.20897839},
{"learn":[0.8758883141],"iteration":41,"passed_time":0.8331725357,"remaining_time":19.00426879},
{"learn":[0.8757561308],"iteration":42,"passed_time":0.8522964009,"remaining_time":18.96855013},
{"learn":[0.8756565224],"iteration":43,"passed_time":0.8667255888,"remaining_time":18.83158325},
{"learn":[0.875624152],"iteration":44,"passed_time":0.8740950791,"remaining_time":18.55024001},
{"learn":[0.8755379496],"iteration":45,"passed_time":0.8840801468,"remaining_time":18.33505348},
{"learn":[0.8754163937],"iteration":46,"passed_time":0.8966879549,"remaining_time":18.18177917},
{"learn":[0.8753419385],"iteration":47,"passed_time":0.9076909277,"remaining_time":18.00253673},
{"learn":[0.8752624521],"iteration":48,"passed_time":0.9203343116,"remaining_time":17.86199858},
{"learn":[0.8751887315],"iteration":49,"passed_time":0.9511880673,"remaining_time":18.07257328},
{"learn":[0.8751189939],"iteration":50,"passed_time":0.9722316471,"remaining_time":18.09113398},
{"learn":[0.8750610773],"iteration":51,"passed_time":0.9864658535,"remaining_time":17.98403133},
{"learn":[0.8749695597],"iteration":52,"passed_time":1.004846997,"remaining_time":17.9545303},
{"learn":[0.8749186723],"iteration":53,"passed_time":1.065670354,"remaining_time":18.66896583},
{"learn":[0.8748486994],"iteration":54,"passed_time":1.102719754,"remaining_time":18.94673031},
{"learn":[0.8747916239],"iteration":55,"passed_time":1.123039419,"remaining_time":18.93123592},
{"learn":[0.8747007027],"iteration":56,"passed_time":1.14220811,"remaining_time":18.89653065},
{"learn":[0.874626901],"iteration":57,"passed_time":1.155063479,"remaining_time":18.75982408},
{"learn":[0.8745408886],"iteration":58,"passed_time":1.171128621,"remaining_time":18.67850902},
{"learn":[0.8744534163],"iteration":59,"passed_time":1.186230361,"remaining_time":18.58427565},
{"learn":[0.8743667579],"iteration":60,"passed_time":1.202184155,"remaining_time":18.50575282},
{"learn":[0.874248464],"iteration":61,"passed_time":1.215847478,"remaining_time":18.39459571},
{"learn":[0.8741839337],"iteration":62,"passed_time":1.230905766,"remaining_time":18.307281},
{"learn":[0.8741028137],"iteration":63,"passed_time":1.246970154,"remaining_time":18.2369385},
{"learn":[0.8740631045],"iteration":64,"passed_time":1.262742866,"remaining_time":18.16407046},
{"learn":[0.8739281856],"iteration":65,"passed_time":1.277610426,"remaining_time":18.08012331},
{"learn":[0.8738335382],"iteration":66,"passed_time":1.291853339,"remaining_time":17.98953978},
{"learn":[0.8737100679],"iteration":67,"passed_time":1.302357609,"remaining_time":17.84996017},
{"learn":[0.8736415257],"iteration":68,"passed_time":1.316972138,"remaining_time":17.76958059},
{"learn":[0.8735851052],"iteration":69,"passed_time":1.334180922,"remaining_time":17.72554654},
{"learn":[0.8734860676],"iteration":70,"passed_time":1.351064719,"remaining_time":17.67801582},
{"learn":[0.8733927546],"iteration":71,"passed_time":1.363554517,"remaining_time":17.57470266},
{"learn":[0.873264461],"iteration":72,"passed_time":1.375336753,"remaining_time":17.46489275},
{"learn":[0.8731886505],"iteration":73,"passed_time":1.386537078,"remaining_time":17.35045047},
{"learn":[0.8731473247],"iteration":74,"passed_time":1.395476668,"remaining_time":17.21087891},
{"learn":[0.8730973991],"iteration":75,"passed_time":1.408763338,"remaining_time":17.12759637},
{"learn":[0.873034571],"iteration":76,"passed_time":1.428058378,"remaining_time":17.11815432},
{"learn":[0.8729601749],"iteration":77,"passed_time":1.44370101,"remaining_time":17.0652863},
{"learn":[0.8728668842],"iteration":78,"passed_time":1.458829769,"remaining_time":17.00736984},
{"learn":[0.8728122658],"iteration":79,"passed_time":1.477889154,"remaining_time":16.99572527},
{"learn":[0.8727163877],"iteration":80,"passed_time":1.4928532,"remaining_time":16.93743322},
{"learn":[0.8726433061],"iteration":81,"passed_time":1.5074804,"remaining_time":16.87642691},
{"learn":[0.8726046357],"iteration":82,"passed_time":1.521234887,"remaining_time":16.80689628},
{"learn":[0.872556341],"iteration":83,"passed_time":1.533992732,"remaining_time":16.72782551},
{"learn":[0.8724660282],"iteration":84,"passed_time":1.543755914,"remaining_time":16.61807837},
{"learn":[0.8723703057],"iteration":85,"passed_time":1.557043346,"remaining_time":16.54811184},
{"learn":[0.872264024],"iteration":86,"passed_time":1.570828471,"remaining_time":16.48467119},
{"learn":[0.8722116927],"iteration":87,"passed_time":1.582880385,"remaining_time":16.40439672},
{"learn":[0.8721505127],"iteration":88,"passed_time":1.598533784,"remaining_time":16.36251997},
{"learn":[0.8720845082],"iteration":89,"passed_time":1.617738198,"remaining_time":16.35713067},
{"learn":[0.8720217443],"iteration":90,"passed_time":1.628920424,"remaining_time":16.27130401},
{"learn":[0.8719635339],"iteration":91,"passed_time":1.6388858,"remaining_time":16.17509028},
{"learn":[0.8718110125],"iteration":92,"passed_time":1.652005757,"remaining_time":16.11149701},
{"learn":[0.871725817],"iteration":93,"passed_time":1.664232874,"remaining_time":16.04037217},
{"learn":[0.8716545027],"iteration":94,"passed_time":1.673340893,"remaining_time":15.94077377},
{"learn":[0.8715481623],"iteration":95,"passed_time":1.686100548,"remaining_time":15.87744683},
{"learn":[0.8714749593],"iteration":96,"passed_time":1.69801491,"remaining_time":15.80729344},
{"learn":[0.8714102062],"iteration":97,"passed_time":1.706928711,"remaining_time":15.7107112},
{"learn":[0.8713581367],"iteration":98,"passed_time":1.718270671,"remaining_time":15.63799873},
{"learn":[0.8712701763],"iteration":99,"passed_time":1.729955887,"remaining_time":15.56960298},
{"learn":[0.8711176422],"iteration":100,"passed_time":1.738725981,"remaining_time":15.47638274},
{"learn":[0.8710413615],"iteration":101,"passed_time":1.750293238,"remaining_time":15.40944439},
{"learn":[0.8709270774],"iteration":102,"passed_time":1.763252643,"remaining_time":15.35570506},
{"learn":[0.8708204789],"iteration":103,"passed_time":1.775092958,"remaining_time":15.29310856},
{"learn":[0.8707525578],"iteration":104,"passed_time":1.78463081,"remaining_time":15.21185309},
{"learn":[0.8706340972],"iteration":105,"passed_time":1.799302432,"remaining_time":15.17524882},
{"learn":[0.8705907],"iteration":106,"passed_time":1.81164731,"remaining_time":15.11963596},
{"learn":[0.8704458432],"iteration":107,"passed_time":1.822238596,"remaining_time":15.050341},
{"learn":[0.8703709805],"iteration":108,"passed_time":1.832586138,"remaining_time":14.98013073},
{"learn":[0.8702972443],"iteration":109,"passed_time":1.842871013,"remaining_time":14.91050184},
{"learn":[0.8702131081],"iteration":110,"passed_time":1.850671026,"remaining_time":14.82204092},
{"learn":[0.8701738301],"iteration":111,"passed_time":1.860165087,"remaining_time":14.74845177},
{"learn":[0.8700489836],"iteration":112,"passed_time":1.868108354,"remaining_time":14.66382398},
{"learn":[0.8699942305],"iteration":113,"passed_time":1.878153776,"remaining_time":14.59687935},
{"learn":[0.8699495002],"iteration":114,"passed_time":1.885912375,"remaining_time":14.51332567},
{"learn":[0.869862332],"iteration":115,"passed_time":1.895308046,"remaining_time":14.44355442},
{"learn":[0.8697614125],"iteration":116,"passed_time":1.907297892,"remaining_time":14.39439349},
{"learn":[0.869669885],"iteration":117,"passed_time":1.915785712,"remaining_time":14.31968642},
{"learn":[0.8695233505],"iteration":118,"passed_time":1.926111197,"remaining_time":14.25969718},
{"learn":[0.8694889849],"iteration":119,"passed_time":1.933938762,"remaining_time":14.18221759},
{"learn":[0.8694124124],"iteration":120,"passed_time":1.94269155,"remaining_time":14.11261052},
{"learn":[0.8693332962],"iteration":121,"passed_time":1.950900568,"remaining_time":14.0400877},
{"learn":[0.8692908965],"iteration":122,"passed_time":1.959141292,"remaining_time":13.96883669},
{"learn":[0.869211594],"iteration":123,"passed_time":1.970551933,"remaining_time":13.92099591},
{"learn":[0.8690927766],"iteration":124,"passed_time":1.979727709,"remaining_time":13.85809396},
{"learn":[0.8690490223],"iteration":125,"passed_time":1.989824217,"remaining_time":13.80243148},
{"learn":[0.8690028005],"iteration":126,"passed_time":1.99749111,"remaining_time":13.73078534},
{"learn":[0.8689247323],"iteration":127,"passed_time":2.005907863,"remaining_time":13.66524732},
{"learn":[0.8688243268],"iteration":128,"passed_time":2.014233361,"remaining_time":13.59997874},
{"learn":[0.8687688674],"iteration":129,"passed_time":2.026653271,"remaining_time":13.56298728},
{"learn":[0.8686915774],"iteration":130,"passed_time":2.036226321,"remaining_time":13.50748605},
{"learn":[0.8686038797],"iteration":131,"passed_time":2.044499757,"remaining_time":13.44413476},
{"learn":[0.8685383442],"iteration":132,"passed_time":2.052686962,"remaining_time":13.38104959},
{"learn":[0.8685036761],"iteration":133,"passed_time":2.06016661,"remaining_time":13.31421108},
{"learn":[0.8684004487],"iteration":134,"passed_time":2.070185909,"remaining_time":13.26452453},
{"learn":[0.8683474247],"iteration":135,"passed_time":2.078404451,"remaining_time":13.20398122},
{"learn":[0.8682977584],"iteration":136,"passed_time":2.087762382,"remaining_time":13.15137909},
{"learn":[0.8682356271],"iteration":137,"passed_time":2.096417312,"remaining_time":13.09501249},
{"learn":[0.8681719044],"iteration":138,"passed_time":2.104579367,"remaining_time":13.03627939},
{"learn":[0.8680783952],"iteration":139,"passed_time":2.113844625,"remaining_time":12.98504555},
{"learn":[0.8679643148],"iteration":140,"passed_time":2.123112398,"remaining_time":12.93442234},
{"learn":[0.8678858796],"iteration":141,"passed_time":2.133041081,"remaining_time":12.88837498},
{"learn":[0.8677659339],"iteration":142,"passed_time":2.141202512,"remaining_time":12.83224163},
{"learn":[0.8676519402],"iteration":143,"passed_time":2.149992958,"remaining_time":12.7805137},
{"learn":[0.8675606638],"iteration":144,"passed_time":2.159155053,"remaining_time":12.73156945},
{"learn":[0.8674518206],"iteration":145,"passed_time":2.16934466,"remaining_time":12.68918041},
{"learn":[0.8674108889],"iteration":146,"passed_time":2.178844681,"remaining_time":12.64322798},
{"learn":[0.86734915],"iteration":147,"passed_time":2.187426869,"remaining_time":12.59248441},
{"learn":[0.8672943038],"iteration":148,"passed_time":2.194924972,"remaining_time":12.53611511},
{"learn":[0.8671860048],"iteration":149,"passed_time":2.202781997,"remaining_time":12.48243132},
{"learn":[0.8671129685],"iteration":150,"passed_time":2.212246462,"remaining_time":12.43839236},
{"learn":[0.8670063753],"iteration":151,"passed_time":2.220946807,"remaining_time":12.39054534},
{"learn":[0.8669220517],"iteration":152,"passed_time":2.229827704,"remaining_time":12.34420958},
{"learn":[0.8668943189],"iteration":153,"passed_time":2.236700423,"remaining_time":12.2873283},
{"learn":[0.8668116111],"iteration":154,"passed_time":2.245305248,"remaining_time":12.24053506},
{"learn":[0.8666795627],"iteration":155,"passed_time":2.252758871,"remaining_time":12.18800312},
{"learn":[0.8665243755],"iteration":156,"passed_time":2.262528019,"remaining_time":12.14847847},
{"learn":[0.8664258665],"iteration":157,"passed_time":2.270337229,"remaining_time":12.09888574},
{"learn":[0.866344541],"iteration":158,"passed_time":2.279772948,"remaining_time":12.05842169},
{"learn":[0.8662312774],"iteration":159,"passed_time":2.288298187,"remaining_time":12.01356548},
{"learn":[0.8660742462],"iteration":160,"passed_time":2.298095247,"remaining_time":11.97578827},
{"learn":[0.865959568],"iteration":161,"passed_time":2.310082631,"remaining_time":11.9496867},
{"learn":[0.8658641152],"iteration":162,"passed_time":2.318905829,"remaining_time":11.9075103},
{"learn":[0.8657706126],"iteration":163,"passed_time":2.330556297,"remaining_time":11.88015283},
{"learn":[0.8656649548],"iteration":164,"passed_time":2.33951573,"remaining_time":11.83936748},
{"learn":[0.8655344838],"iteration":165,"passed_time":2.350825689,"remaining_time":11.81077485},
{"learn":[0.8654700301],"iteration":166,"passed_time":2.362430814,"remaining_time":11.78386148},
{"learn":[0.865378813],"iteration":167,"passed_time":2.371798929,"remaining_time":11.74605184},
{"learn":[0.8652949536],"iteration":168,"passed_time":2.380750718,"remaining_time":11.70653164},
{"learn":[0.865193724],"iteration":169,"passed_time":2.391408101,"remaining_time":11.67569838},
{"learn":[0.8650957078],"iteration":170,"passed_time":2.399735264,"remaining_time":11.63380429},
{"learn":[0.8649983929],"iteration":171,"passed_time":2.410700477,"remaining_time":11.60499997},
{"learn":[0.864848514],"iteration":172,"passed_time":2.42008628,"remaining_time":11.56885175},
{"learn":[0.864727991],"iteration":173,"passed_time":2.428271571,"remaining_time":11.52731217},
{"learn":[0.8646161836],"iteration":174,"passed_time":2.436176159,"remaining_time":11.48483046},
{"learn":[0.8645440303],"iteration":175,"passed_time":2.444159008,"remaining_time":11.44310808},
{"learn":[0.8644759619],"iteration":176,"passed_time":2.452806746,"remaining_time":11.40485848},
{"learn":[0.864352475],"iteration":177,"passed_time":2.461493823,"remaining_time":11.36712316},
{"learn":[0.8642006018],"iteration":178,"passed_time":2.471353322,"remaining_time":11.33508982},
{"learn":[0.8640739388],"iteration":179,"passed_time":2.479374588,"remaining_time":11.29492868},
{"learn":[0.8639364644],"iteration":180,"passed_time":2.48775569,"remaining_time":11.25675088},
{"learn":[0.8637929135],"iteration":181,"passed_time":2.496195207,"remaining_time":11.21916308},
{"learn":[0.8636958007],"iteration":182,"passed_time":2.506327861,"remaining_time":11.1894528},
{"learn":[0.8635782054],"iteration":183,"passed_time":2.515175856,"remaining_time":11.15425815},
{"learn":[0.8634958703],"iteration":184,"passed_time":2.523679528,"remaining_time":11.11783144},
{"learn":[0.863428584],"iteration":185,"passed_time":2.532011131,"remaining_time":11.08095194},
{"learn":[0.8633014765],"iteration":186,"passed_time":2.540097045,"remaining_time":11.04330961},
{"learn":[0.8632230764],"iteration":187,"passed_time":2.547951228,"remaining_time":11.00498083},
{"learn":[0.8631173669],"iteration":188,"passed_time":2.557545871,"remaining_time":10.97444286},
{"learn":[0.8630368048],"iteration":189,"passed_time":2.567057791,"remaining_time":10.94377269},
{"learn":[0.8629335159],"iteration":190,"passed_time":2.575453958,"remaining_time":10.90859818},
{"learn":[0.8628357288],"iteration":191,"passed_time":2.583240524,"remaining_time":10.87113721},
{"learn":[0.862740515],"iteration":192,"passed_time":2.59280688,"remaining_time":10.84142566},
{"learn":[0.8626849149],"iteration":193,"passed_time":2.602614607,"remaining_time":10.81292461},
{"learn":[0.8625562437],"iteration":194,"passed_time":2.612299963,"remaining_time":10.7841101},
{"learn":[0.8624497114],"iteration":195,"passed_time":2.620964867,"remaining_time":10.75130486},
{"learn":[0.8623838859],"iteration":196,"passed_time":2.629437599,"remaining_time":10.71796138},
{"learn":[0.8623121078],"iteration":197,"passed_time":2.639025987,"remaining_time":10.68938809},
{"learn":[0.862220837],"iteration":198,"passed_time":2.649647463,"remaining_time":10.66516391},
{"learn":[0.8620783321],"iteration":199,"passed_time":2.661200807,"remaining_time":10.64480323},
{"learn":[0.8619640678],"iteration":200,"passed_time":2.669531827,"remaining_time":10.61172104},
{"learn":[0.8618224324],"iteration":201,"passed_time":2.677964937,"remaining_time":10.57928723},
{"learn":[0.8617034755],"iteration":202,"passed_time":2.686160424,"remaining_time":10.54615693},
{"learn":[0.8615952504],"iteration":203,"passed_time":2.695433146,"remaining_time":10.51747443},
{"learn":[0.8614513325],"iteration":204,"passed_time":2.70433476,"remaining_time":10.48754212},
{"learn":[0.861312293],"iteration":205,"passed_time":2.71393392,"remaining_time":10.46050258},
{"learn":[0.8612067085],"iteration":206,"passed_time":2.72171544,"remaining_time":10.42666833},
{"learn":[0.8611290378],"iteration":207,"passed_time":2.729544739,"remaining_time":10.39326651},
{"learn":[0.8610922098],"iteration":208,"passed_time":2.737386053,"remaining_time":10.36015487},
{"learn":[0.8610112673],"iteration":209,"passed_time":2.747332747,"remaining_time":10.33520414},
{"learn":[0.8609326138],"iteration":210,"passed_time":2.755361646,"remaining_time":10.30322436},
{"learn":[0.860844339],"iteration":211,"passed_time":2.764599373,"remaining_time":10.27596371},
{"learn":[0.8607624208],"iteration":212,"passed_time":2.773228807,"remaining_time":10.24662475},
{"learn":[0.8606838127],"iteration":213,"passed_time":2.782362138,"remaining_time":10.21933009},
{"learn":[0.8604972944],"iteration":214,"passed_time":2.79249148,"remaining_time":10.19584099},
{"learn":[0.8604133893],"iteration":215,"passed_time":2.800791896,"remaining_time":10.16583725},
{"learn":[0.8602720167],"iteration":216,"passed_time":2.811008761,"remaining_time":10.14294866},
{"learn":[0.8601039335],"iteration":217,"passed_time":2.819324002,"remaining_time":10.11335491},
{"learn":[0.8600178179],"iteration":218,"passed_time":2.828249416,"remaining_time":10.08613148},
{"learn":[0.8598933256],"iteration":219,"passed_time":2.836767775,"remaining_time":10.0576312},
{"learn":[0.8598230423],"iteration":220,"passed_time":2.847024039,"remaining_time":10.03543767},
{"learn":[0.859684759],"iteration":221,"passed_time":2.856781056,"remaining_time":10.01160208},
{"learn":[0.8595679048],"iteration":222,"passed_time":2.866557556,"remaining_time":9.987960633},
{"learn":[0.8594909134],"iteration":223,"passed_time":2.876289643,"remaining_time":9.964289122},
{"learn":[0.8594045828],"iteration":224,"passed_time":2.884410986,"remaining_time":9.935193396},
{"learn":[0.8593135887],"iteration":225,"passed_time":2.894777675,"remaining_time":9.913973099},
{"learn":[0.8592039608],"iteration":226,"passed_time":2.905123127,"remaining_time":9.892776112},
{"learn":[0.8591272289],"iteration":227,"passed_time":2.913568216,"remaining_time":9.865239749},
{"learn":[0.85901701],"iteration":228,"passed_time":2.922133642,"remaining_time":9.838275275},
{"learn":[0.8588930624],"iteration":229,"passed_time":2.930241292,"remaining_time":9.809938239},
{"learn":[0.8587889169],"iteration":230,"passed_time":2.941748784,"remaining_time":9.793094435},
{"learn":[0.858707192],"iteration":231,"passed_time":2.949151446,"remaining_time":9.762708235},
{"learn":[0.8586005015],"iteration":232,"passed_time":2.958440988,"remaining_time":9.738730634},
{"learn":[0.8585334848],"iteration":233,"passed_time":2.967820731,"remaining_time":9.715173847},
{"learn":[0.8583997746],"iteration":234,"passed_time":2.975748407,"remaining_time":9.687010771},
{"learn":[0.8583459279],"iteration":235,"passed_time":2.983349864,"remaining_time":9.657963119},
{"learn":[0.8582341146],"iteration":236,"passed_time":2.993367727,"remaining_time":9.636875847},
{"learn":[0.8581534873],"iteration":237,"passed_time":3.002981344,"remaining_time":9.614587328},
{"learn":[0.8581077456],"iteration":238,"passed_time":3.012022623,"remaining_time":9.590582495},
{"learn":[0.8580238497],"iteration":239,"passed_time":3.02058216,"remaining_time":9.565176841},
{"learn":[0.8579583383],"iteration":240,"passed_time":3.029085481,"remaining_time":9.539733943},
{"learn":[0.8578824465],"iteration":241,"passed_time":3.039435089,"remaining_time":9.520214039},
{"learn":[0.8578412922],"iteration":242,"passed_time":3.049586558,"remaining_time":9.500152362},
{"learn":[0.8577248502],"iteration":243,"passed_time":3.058243262,"remaining_time":9.475540598},
{"learn":[0.8575815112],"iteration":244,"passed_time":3.06734192,"remaining_time":9.45242102},
{"learn":[0.8575053117],"iteration":245,"passed_time":3.076747657,"remaining_time":9.430356641},
{"learn":[0.8573878367],"iteration":246,"passed_time":3.088124688,"remaining_time":9.414404413},
{"learn":[0.8573307669],"iteration":247,"passed_time":3.098322403,"remaining_time":9.394913094},
{"learn":[0.8571695088],"iteration":248,"passed_time":3.106826983,"remaining_time":9.370389816},
{"learn":[0.8570419785],"iteration":249,"passed_time":3.11509057,"remaining_time":9.345271709},
{"learn":[0.8569790671],"iteration":250,"passed_time":3.122986651,"remaining_time":9.319191241},
{"learn":[0.8568569515],"iteration":251,"passed_time":3.133353627,"remaining_time":9.300589336},
{"learn":[0.8567085431],"iteration":252,"passed_time":3.142010525,"remaining_time":9.277003408},
{"learn":[0.8565699021],"iteration":253,"passed_time":3.151379045,"remaining_time":9.255625071},
{"learn":[0.8565005963],"iteration":254,"passed_time":3.159861632,"remaining_time":9.231752612},
{"learn":[0.8563224972],"iteration":255,"passed_time":3.169536283,"remaining_time":9.211464822},
{"learn":[0.8562053557],"iteration":256,"passed_time":3.180485691,"remaining_time":9.194945013},
{"learn":[0.8561199123],"iteration":257,"passed_time":3.188915583,"remaining_time":9.171222335},
{"learn":[0.8560054897],"iteration":258,"passed_time":3.198815693,"remaining_time":9.151824049},
{"learn":[0.8559474452],"iteration":259,"passed_time":3.207030318,"remaining_time":9.127701673},
{"learn":[0.8558584008],"iteration":260,"passed_time":3.214875601,"remaining_time":9.102655436},
{"learn":[0.8557494072],"iteration":261,"passed_time":3.224369711,"remaining_time":9.08238491},
{"learn":[0.8556830114],"iteration":262,"passed_time":3.234022359,"remaining_time":9.062640602},
{"learn":[0.8556108009],"iteration":263,"passed_time":3.243231602,"remaining_time":9.041736586},
{"learn":[0.855539866],"iteration":264,"passed_time":3.251400849,"remaining_time":9.018036316},
{"learn":[0.8554552233],"iteration":265,"passed_time":3.259977766,"remaining_time":8.995577745},
{"learn":[0.8553482579],"iteration":266,"passed_time":3.26912638,"remaining_time":8.974792647},
{"learn":[0.8552610372],"iteration":267,"passed_time":3.279018563,"remaining_time":8.95612533},
{"learn":[0.8551498291],"iteration":268,"passed_time":3.287924528,"remaining_time":8.934843233},
{"learn":[0.8550424864],"iteration":269,"passed_time":3.299759667,"remaining_time":8.921572434},
{"learn":[0.8549427882],"iteration":270,"passed_time":3.308970175,"remaining_time":8.901251873},
{"learn":[0.8548426323],"iteration":271,"passed_time":3.316785833,"remaining_time":8.877279729},
{"learn":[0.8547532876],"iteration":272,"passed_time":3.326475441,"remaining_time":8.858416284},
{"learn":[0.8546483996],"iteration":273,"passed_time":3.334781985,"remaining_time":8.835955187},
{"learn":[0.8545524169],"iteration":274,"passed_time":3.343995092,"remaining_time":8.81598706},
{"learn":[0.8544435097],"iteration":275,"passed_time":3.352639561,"remaining_time":8.794605226},
{"learn":[0.8543334919],"iteration":276,"passed_time":3.36360429,"remaining_time":8.779371486},
{"learn":[0.8542376094],"iteration":277,"passed_time":3.37435913,"remaining_time":8.763623353},
{"learn":[0.854182141],"iteration":278,"passed_time":3.382494619,"remaining_time":8.741142009},
{"learn":[0.854058921],"iteration":279,"passed_time":3.392477542,"remaining_time":8.723513681},
{"learn":[0.8540112785],"iteration":280,"passed_time":3.399928374,"remaining_time":8.699460857},
{"learn":[0.8539015689],"iteration":281,"passed_time":3.408237643,"remaining_time":8.677711445},
{"learn":[0.8537754975],"iteration":282,"passed_time":3.416151517,"remaining_time":8.655055256},
{"learn":[0.8536613467],"iteration":283,"passed_time":3.426873964,"remaining_time":8.639583655},
{"learn":[0.8535804073],"iteration":284,"passed_time":3.436099088,"remaining_time":8.620388941},
{"learn":[0.8534887018],"iteration":285,"passed_time":3.444408727,"remaining_time":8.59897843},
{"learn":[0.8533984058],"iteration":286,"passed_time":3.452407529,"remaining_time":8.576886996},
{"learn":[0.8533035251],"iteration":287,"passed_time":3.460404426,"remaining_time":8.55488872},
{"learn":[0.853235467],"iteration":288,"passed_time":3.468941668,"remaining_time":8.534316698},
{"learn":[0.8531350308],"iteration":289,"passed_time":3.477914702,"remaining_time":8.514894615},
{"learn":[0.8530828388],"iteration":290,"passed_time":3.487202362,"remaining_time":8.496310908},
{"learn":[0.8530012287],"iteration":291,"passed_time":3.49606415,"remaining_time":8.476758282},
{"learn":[0.852928253],"iteration":292,"passed_time":3.504967775,"remaining_time":8.45737958},
{"learn":[0.8528637145],"iteration":293,"passed_time":3.512939764,"remaining_time":8.435834942},
{"learn":[0.8527819322],"iteration":294,"passed_time":3.539153931,"remaining_time":8.457978037},
{"learn":[0.8527120791],"iteration":295,"passed_time":3.547591747,"remaining_time":8.437515505},
{"learn":[0.8526194441],"iteration":296,"passed_time":3.556055475,"remaining_time":8.417195282},
{"learn":[0.8525551571],"iteration":297,"passed_time":3.564188818,"remaining_time":8.396176344},
{"learn":[0.8524719785],"iteration":298,"passed_time":3.575076764,"remaining_time":8.381701711},
{"learn":[0.852388727],"iteration":299,"passed_time":3.58501252,"remaining_time":8.365029212},
{"learn":[0.8522879329],"iteration":300,"passed_time":3.592957256,"remaining_time":8.343777813},
{"learn":[0.8522117395],"iteration":301,"passed_time":3.601839715,"remaining_time":8.324781858},
{"learn":[0.852104487],"iteration":302,"passed_time":3.609607949,"remaining_time":8.303289573},
{"learn":[0.8520474836],"iteration":303,"passed_time":3.619070126,"remaining_time":8.285765815},
{"learn":[0.8519842764],"iteration":304,"passed_time":3.62700587,"remaining_time":8.264816655},
{"learn":[0.851868483],"iteration":305,"passed_time":3.637385818,"remaining_time":8.24949594},
{"learn":[0.8518036489],"iteration":306,"passed_time":3.64610067,"remaining_time":8.230448744},
{"learn":[0.8516623751],"iteration":307,"passed_time":3.656083701,"remaining_time":8.214317925},
{"learn":[0.8516119124],"iteration":308,"passed_time":3.666631938,"remaining_time":8.199490839},
{"learn":[0.8515661672],"iteration":309,"passed_time":3.675112983,"remaining_time":8.180090189},
{"learn":[0.851468114],"iteration":310,"passed_time":3.68423817,"remaining_time":8.162186815},
{"learn":[0.8513567926],"iteration":311,"passed_time":3.692423888,"remaining_time":8.142268062},
{"learn":[0.8512868827],"iteration":312,"passed_time":3.700722385,"remaining_time":8.122671817},
{"learn":[0.8512015986],"iteration":313,"passed_time":3.709068872,"remaining_time":8.103252375},
{"learn":[0.851083492],"iteration":314,"passed_time":3.719366381,"remaining_time":8.088145939},
{"learn":[0.8509917447],"iteration":315,"passed_time":3.728416417,"remaining_time":8.070369712},
{"learn":[0.8509519912],"iteration":316,"passed_time":3.736632857,"remaining_time":8.050852497},
{"learn":[0.8508598466],"iteration":317,"passed_time":3.745899171,"remaining_time":8.033657971},
{"learn":[0.850798553],"iteration":318,"passed_time":3.753576536,"remaining_time":8.013121069},
{"learn":[0.8506922423],"iteration":319,"passed_time":3.763800244,"remaining_time":7.998075519},
{"learn":[0.8506062019],"iteration":320,"passed_time":3.772758448,"remaining_time":7.980383135},
{"learn":[0.850558711],"iteration":321,"passed_time":3.782328872,"remaining_time":7.964034084},
{"learn":[0.8505079597],"iteration":322,"passed_time":3.790794721,"remaining_time":7.945411846},
{"learn":[0.8504555962],"iteration":323,"passed_time":3.800240931,"remaining_time":7.928897745},
{"learn":[0.8504098634],"iteration":324,"passed_time":3.810409564,"remaining_time":7.913927557},
{"learn":[0.8503261297],"iteration":325,"passed_time":3.818638185,"remaining_time":7.894975879},
{"learn":[0.850235358],"iteration":326,"passed_time":3.828796905,"remaining_time":7.880062131},
{"learn":[0.8501802526],"iteration":327,"passed_time":3.837662317,"remaining_time":7.862527674},
{"learn":[0.8501009964],"iteration":328,"passed_time":3.846384675,"remaining_time":7.844754155},
{"learn":[0.8499878087],"iteration":329,"passed_time":3.855143051,"remaining_time":7.827108618},
{"learn":[0.8498722962],"iteration":330,"passed_time":3.865162449,"remaining_time":7.812065495},
{"learn":[0.8498076026],"iteration":331,"passed_time":3.875427028,"remaining_time":7.797545948},
{"learn":[0.8496852362],"iteration":332,"passed_time":3.886286926,"remaining_time":7.784244383},
{"learn":[0.8495576372],"iteration":333,"passed_time":3.895928504,"remaining_time":7.768528094},
{"learn":[0.8494521691],"iteration":334,"passed_time":3.908053942,"remaining_time":7.75777872},
{"learn":[0.8493602663],"iteration":335,"passed_time":3.916485086,"remaining_time":7.739720527},
{"learn":[0.849298257],"iteration":336,"passed_time":3.925670061,"remaining_time":7.723202523},
{"learn":[0.8492129119],"iteration":337,"passed_time":3.933658985,"remaining_time":7.704385349},
{"learn":[0.8491267421],"iteration":338,"passed_time":3.942150736,"remaining_time":7.686612498},
{"learn":[0.8490820427],"iteration":339,"passed_time":3.949812204,"remaining_time":7.667282514},
{"learn":[0.8489710527],"iteration":340,"passed_time":3.959899929,"remaining_time":7.652709833},
{"learn":[0.8488446446],"iteration":341,"passed_time":3.968720483,"remaining_time":7.635725373},
{"learn":[0.8487323006],"iteration":342,"passed_time":3.977565406,"remaining_time":7.618835195},
{"learn":[0.848650945],"iteration":343,"passed_time":3.989975399,"remaining_time":7.608790295},
{"learn":[0.8485541022],"iteration":344,"passed_time":4.004511592,"remaining_time":7.602768384},
{"learn":[0.8484316428],"iteration":345,"passed_time":4.018562483,"remaining_time":7.595779954},
{"learn":[0.8483666345],"iteration":346,"passed_time":4.030169727,"remaining_time":7.584152253},
{"learn":[0.8482697068],"iteration":347,"passed_time":4.042451588,"remaining_time":7.573788607},
{"learn":[0.8481724711],"iteration":348,"passed_time":4.056590077,"remaining_time":7.566877193},
{"learn":[0.8481114468],"iteration":349,"passed_time":4.070180778,"remaining_time":7.558907159},
{"learn":[0.8479896455],"iteration":350,"passed_time":4.083042959,"remaining_time":7.549558064},
{"learn":[0.8479047512],"iteration":351,"passed_time":4.094541279,"remaining_time":7.537678263},
{"learn":[0.8477708816],"iteration":352,"passed_time":4.108742239,"remaining_time":7.530754188},
{"learn":[0.8477145968],"iteration":353,"passed_time":4.121947927,"remaining_time":7.52197277},
{"learn":[0.8476579181],"iteration":354,"passed_time":4.133350047,"remaining_time":7.509889522},
{"learn":[0.847564231],"iteration":355,"passed_time":4.145441316,"remaining_time":7.499056763},
{"learn":[0.8474462407],"iteration":356,"passed_time":4.161317102,"remaining_time":7.495033324},
{"learn":[0.847353543],"iteration":357,"passed_time":4.176795848,"remaining_time":7.49023166},
{"learn":[0.8472648107],"iteration":358,"passed_time":4.189401618,"remaining_time":7.480240772},
{"learn":[0.8471359129],"iteration":359,"passed_time":4.203623204,"remaining_time":7.473107918},
{"learn":[0.8470249313],"iteration":360,"passed_time":4.215795217,"remaining_time":7.462307878},
{"learn":[0.8469126644],"iteration":361,"passed_time":4.226916797,"remaining_time":7.44964894},
{"learn":[0.8468419258],"iteration":362,"passed_time":4.237706015,"remaining_time":7.436415238},
{"learn":[0.8467433096],"iteration":363,"passed_time":4.25000167,"remaining_time":7.425827094},
{"learn":[0.8466709057],"iteration":364,"passed_time":4.260549312,"remaining_time":7.412188529},
{"learn":[0.8466003437],"iteration":365,"passed_time":4.270604608,"remaining_time":7.397713993},
{"learn":[0.8465628044],"iteration":366,"passed_time":4.280342499,"remaining_time":7.382716082},
{"learn":[0.8464421424],"iteration":367,"passed_time":4.290439679,"remaining_time":7.368363797},
{"learn":[0.8463598893],"iteration":368,"passed_time":4.301919621,"remaining_time":7.356399135},
{"learn":[0.8462908834],"iteration":369,"passed_time":4.313174516,"remaining_time":7.344053905},
{"learn":[0.8461587892],"iteration":370,"passed_time":4.32494409,"remaining_time":7.33258715},
{"learn":[0.8460765129],"iteration":371,"passed_time":4.335842893,"remaining_time":7.319648755},
{"learn":[0.8460305239],"iteration":372,"passed_time":4.347190853,"remaining_time":7.307476313},
{"learn":[0.8459542785],"iteration":373,"passed_time":4.357868558,"remaining_time":7.294186409},
{"learn":[0.8458706769],"iteration":374,"passed_time":4.367420911,"remaining_time":7.279034852},
{"learn":[0.8457743995],"iteration":375,"passed_time":4.381432543,"remaining_time":7.271313582},
{"learn":[0.8457019243],"iteration":376,"passed_time":4.394621923,"remaining_time":7.262200154},
{"learn":[0.8456177658],"iteration":377,"passed_time":4.405815109,"remaining_time":7.249780417},
{"learn":[0.8455372794],"iteration":378,"passed_time":4.415936922,"remaining_time":7.235611684},
{"learn":[0.8454651544],"iteration":379,"passed_time":4.426558521,"remaining_time":7.222279692},
{"learn":[0.8454096452],"iteration":380,"passed_time":4.437324034,"remaining_time":7.209195739},
{"learn":[0.8453296088],"iteration":381,"passed_time":4.44824482,"remaining_time":7.196375128},
{"learn":[0.845249013],"iteration":382,"passed_time":4.459378857,"remaining_time":7.183907975},
{"learn":[0.8451995362],"iteration":383,"passed_time":4.469802286,"remaining_time":7.170307834},
{"learn":[0.8451043995],"iteration":384,"passed_time":4.478090713,"remaining_time":7.153313737},
{"learn":[0.8449967332],"iteration":385,"passed_time":4.488628521,"remaining_time":7.139942776},
{"learn":[0.8449481227],"iteration":386,"passed_time":4.498385352,"remaining_time":7.125349408},
{"learn":[0.8448632808],"iteration":387,"passed_time":4.509762596,"remaining_time":7.113336879},
{"learn":[0.8447599815],"iteration":388,"passed_time":4.520520046,"remaining_time":7.100354108},
{"learn":[0.8447076071],"iteration":389,"passed_time":4.529664285,"remaining_time":7.084859522},
{"learn":[0.8445977289],"iteration":390,"passed_time":4.542450571,"remaining_time":7.07507007},
{"learn":[0.8444884235],"iteration":391,"passed_time":4.554030205,"remaining_time":7.063393787},
{"learn":[0.8443934499],"iteration":392,"passed_time":4.562738502,"remaining_time":7.047283131},
{"learn":[0.8443061337],"iteration":393,"passed_time":4.573770523,"remaining_time":7.034784104},
{"learn":[0.8442286529],"iteration":394,"passed_time":4.586457601,"remaining_time":7.024827465},
{"learn":[0.8441099845],"iteration":395,"passed_time":4.598149947,"remaining_time":7.013339818},
{"learn":[0.8440051498],"iteration":396,"passed_time":4.608357606,"remaining_time":6.999596062},
{"learn":[0.8439081424],"iteration":397,"passed_time":4.618680163,"remaining_time":6.986043865},
{"learn":[0.8438665604],"iteration":398,"passed_time":4.625803383,"remaining_time":6.967688805},
{"learn":[0.8437769467],"iteration":399,"passed_time":4.634834747,"remaining_time":6.95225212},
{"learn":[0.8436621231],"iteration":400,"passed_time":4.64302205,"remaining_time":6.935586553},
{"learn":[0.8435476084],"iteration":401,"passed_time":4.652374071,"remaining_time":6.920695758},
{"learn":[0.843415981],"iteration":402,"passed_time":4.65967142,"remaining_time":6.902788679},
{"learn":[0.8433579875],"iteration":403,"passed_time":4.667452531,"remaining_time":6.885647793},
{"learn":[0.8432837502],"iteration":404,"passed_time":4.676112893,"remaining_time":6.869844867},
{"learn":[0.8432344919],"iteration":405,"passed_time":4.686941686,"remaining_time":6.857249659},
{"learn":[0.8431587428],"iteration":406,"passed_time":4.695193974,"remaining_time":6.840909156},
{"learn":[0.8430322618],"iteration":407,"passed_time":4.703608482,"remaining_time":6.82484368},
{"learn":[0.8429557263],"iteration":408,"passed_time":4.711482278,"remaining_time":6.808034294},
{"learn":[0.8428929759],"iteration":409,"passed_time":4.720248868,"remaining_time":6.792553249},
{"learn":[0.8428353937],"iteration":410,"passed_time":4.728517548,"remaining_time":6.776391328},
{"learn":[0.8427488744],"iteration":411,"passed_time":4.736392252,"remaining_time":6.759705447},
{"learn":[0.8426447058],"iteration":412,"passed_time":4.745072783,"remaining_time":6.744207564},
{"learn":[0.8426078626],"iteration":413,"passed_time":4.752261658,"remaining_time":6.726631236},
{"learn":[0.8424782217],"iteration":414,"passed_time":4.760127332,"remaining_time":6.71005901},
{"learn":[0.842340968],"iteration":415,"passed_time":4.767948868,"remaining_time":6.69346668},
{"learn":[0.8422569425],"iteration":416,"passed_time":4.777499213,"remaining_time":6.679333432},
{"learn":[0.8421527278],"iteration":417,"passed_time":4.786855711,"remaining_time":6.66495221},
{"learn":[0.8420387323],"iteration":418,"passed_time":4.797438086,"remaining_time":6.652294816},
{"learn":[0.8419453633],"iteration":419,"passed_time":4.806891787,"remaining_time":6.638088659},
{"learn":[0.8418826988],"iteration":420,"passed_time":4.815416192,"remaining_time":6.622627019},
{"learn":[0.8418045059],"iteration":421,"passed_time":4.825299218,"remaining_time":6.609059119},
{"learn":[0.8417394441],"iteration":422,"passed_time":4.834065563,"remaining_time":6.593985414},
{"learn":[0.8415877642],"iteration":423,"passed_time":4.843861862,"remaining_time":6.580340643},
{"learn":[0.8414935658],"iteration":424,"passed_time":4.851283412,"remaining_time":6.563501087},
{"learn":[0.8414257184],"iteration":425,"passed_time":4.859272897,"remaining_time":6.547470993},
{"learn":[0.8413362857],"iteration":426,"passed_time":4.867050857,"remaining_time":6.531194709},
{"learn":[0.84128453],"iteration":427,"passed_time":4.877864213,"remaining_time":6.51901479},
{"learn":[0.8411983256],"iteration":428,"passed_time":4.886722309,"remaining_time":6.504238785},
{"learn":[0.8410827015],"iteration":429,"passed_time":4.896972,"remaining_time":6.491334977},
{"learn":[0.840964925],"iteration":430,"passed_time":4.906222028,"remaining_time":6.477123745},
{"learn":[0.8409098004],"iteration":431,"passed_time":4.913529433,"remaining_time":6.460381291},
{"learn":[0.8408341672],"iteration":432,"passed_time":4.925063167,"remaining_time":6.449216665},
{"learn":[0.8407229901],"iteration":433,"passed_time":4.93309517,"remaining_time":6.433483563},
{"learn":[0.8406805791],"iteration":434,"passed_time":4.942336029,"remaining_time":6.419355991},
{"learn":[0.8406114334],"iteration":435,"passed_time":4.949639573,"remaining_time":6.402744769},
{"learn":[0.8404913384],"iteration":436,"passed_time":4.958028523,"remaining_time":6.387574505},
{"learn":[0.8403963167],"iteration":437,"passed_time":4.965970945,"remaining_time":6.371862263},
{"learn":[0.840318478],"iteration":438,"passed_time":4.975447988,"remaining_time":6.358146518},
{"learn":[0.8402181023],"iteration":439,"passed_time":4.982973045,"remaining_time":6.341965693},
{"learn":[0.8400959652],"iteration":440,"passed_time":4.99209839,"remaining_time":6.327852608},
{"learn":[0.8400274192],"iteration":441,"passed_time":5.000082989,"remaining_time":6.312321963},
{"learn":[0.839946122],"iteration":442,"passed_time":5.008219658,"remaining_time":6.297016591},
{"learn":[0.8398683411],"iteration":443,"passed_time":5.016580792,"remaining_time":6.282024595},
{"learn":[0.8397597909],"iteration":444,"passed_time":5.027258486,"remaining_time":6.269951594},
{"learn":[0.8396993642],"iteration":445,"passed_time":5.036663345,"remaining_time":6.256303797},
{"learn":[0.8396424779],"iteration":446,"passed_time":5.044436207,"remaining_time":6.240655978},
{"learn":[0.8395383307],"iteration":447,"passed_time":5.05216045,"remaining_time":6.224983411},
{"learn":[0.8394726815],"iteration":448,"passed_time":5.059685152,"remaining_time":6.209101378},
{"learn":[0.8394061164],"iteration":449,"passed_time":5.06933873,"remaining_time":6.195858448},
{"learn":[0.8393488085],"iteration":450,"passed_time":5.077087961,"remaining_time":6.180313284},
{"learn":[0.8392765619],"iteration":451,"passed_time":5.085908186,"remaining_time":6.166101075},
{"learn":[0.8391587962],"iteration":452,"passed_time":5.093318306,"remaining_time":6.150209963},
{"learn":[0.8390861934],"iteration":453,"passed_time":5.101534757,"remaining_time":6.135325942},
{"learn":[0.8389906726],"iteration":454,"passed_time":5.108913694,"remaining_time":6.119468051},
{"learn":[0.8389116676],"iteration":455,"passed_time":5.118650185,"remaining_time":6.10645987},
{"learn":[0.8388790484],"iteration":456,"passed_time":5.125943516,"remaining_time":6.090563083},
{"learn":[0.8387662529],"iteration":457,"passed_time":5.135052832,"remaining_time":6.076852914},
{"learn":[0.8387215532],"iteration":458,"passed_time":5.142231288,"remaining_time":6.060886986},
{"learn":[0.8386138938],"iteration":459,"passed_time":5.150110203,"remaining_time":6.045781543},
{"learn":[0.8385457482],"iteration":460,"passed_time":5.158745191,"remaining_time":6.031591449},
{"learn":[0.83845483],"iteration":461,"passed_time":5.168575962,"remaining_time":6.018817896},
{"learn":[0.8383568108],"iteration":462,"passed_time":5.176940113,"remaining_time":6.004356027},
{"learn":[0.8382528326],"iteration":463,"passed_time":5.186806066,"remaining_time":5.991655283},
{"learn":[0.8381528731],"iteration":464,"passed_time":5.195323483,"remaining_time":5.97741519},
{"learn":[0.8380845365],"iteration":465,"passed_time":5.20270855,"remaining_time":5.961902072},
{"learn":[0.8380411189],"iteration":466,"passed_time":5.210542929,"remaining_time":5.946936577},
{"learn":[0.8379902944],"iteration":467,"passed_time":5.219505423,"remaining_time":5.933283943},
{"learn":[0.8379050329],"iteration":468,"passed_time":5.228524308,"remaining_time":5.919715154},
{"learn":[0.8378159736],"iteration":469,"passed_time":5.236982392,"remaining_time":5.905533335},
{"learn":[0.8377361261],"iteration":470,"passed_time":5.245201948,"remaining_time":5.891107921},
{"learn":[0.8376914078],"iteration":471,"passed_time":5.252380032,"remaining_time":5.875543765},
{"learn":[0.8375558333],"iteration":472,"passed_time":5.260108901,"remaining_time":5.860628733},
{"learn":[0.8374715866],"iteration":473,"passed_time":5.268476865,"remaining_time":5.846453229},
{"learn":[0.8374011049],"iteration":474,"passed_time":5.277250383,"remaining_time":5.832750424},
{"learn":[0.8373208372],"iteration":475,"passed_time":5.286555054,"remaining_time":5.819653043},
{"learn":[0.8372502359],"iteration":476,"passed_time":5.295013229,"remaining_time":5.805643436},
{"learn":[0.8371771208],"iteration":477,"passed_time":5.303035598,"remaining_time":5.791181134},
{"learn":[0.8371212378],"iteration":478,"passed_time":5.312977342,"remaining_time":5.778833393},
{"learn":[0.8370129165],"iteration":479,"passed_time":5.320876229,"remaining_time":5.764282582},
{"learn":[0.8369065448],"iteration":480,"passed_time":5.329807616,"remaining_time":5.750873498},
{"learn":[0.8368369029],"iteration":481,"passed_time":5.33844865,"remaining_time":5.737170956},
{"learn":[0.8367956588],"iteration":482,"passed_time":5.345929682,"remaining_time":5.722247713},
{"learn":[0.8367436012],"iteration":483,"passed_time":5.353753895,"remaining_time":5.707721094},
{"learn":[0.836687997],"iteration":484,"passed_time":5.363678098,"remaining_time":5.695452001},
{"learn":[0.8366214734],"iteration":485,"passed_time":5.373089815,"remaining_time":5.682650545},
{"learn":[0.8365311312],"iteration":486,"passed_time":5.380978635,"remaining_time":5.668258808},
{"learn":[0.8364332443],"iteration":487,"passed_time":5.389971879,"remaining_time":5.655052464},
{"learn":[0.8363389203],"iteration":488,"passed_time":5.39854658,"remaining_time":5.641425976},
{"learn":[0.8362341894],"iteration":489,"passed_time":5.408854641,"remaining_time":5.629624218},
{"learn":[0.8361752953],"iteration":490,"passed_time":5.418254068,"remaining_time":5.6168866},
{"learn":[0.8360688566],"iteration":491,"passed_time":5.428515091,"remaining_time":5.605052167},
{"learn":[0.8359768976],"iteration":492,"passed_time":5.437741656,"remaining_time":5.592160283},
{"learn":[0.8358760225],"iteration":493,"passed_time":5.445272393,"remaining_time":5.577546216},
{"learn":[0.8357840084],"iteration":494,"passed_time":5.455500839,"remaining_time":5.565712977},
{"learn":[0.8356544671],"iteration":495,"passed_time":5.464001232,"remaining_time":5.552130285},
{"learn":[0.8355615131],"iteration":496,"passed_time":5.47309486,"remaining_time":5.53916844},
{"learn":[0.8354785884],"iteration":497,"passed_time":5.480447179,"remaining_time":5.524466835},
{"learn":[0.8354256011],"iteration":498,"passed_time":5.487891845,"remaining_time":5.509887404},
{"learn":[0.8353685242],"iteration":499,"passed_time":5.495478068,"remaining_time":5.495478068},
{"learn":[0.8352986941],"iteration":500,"passed_time":5.504605977,"remaining_time":5.482631502},
{"learn":[0.8352292145],"iteration":501,"passed_time":5.513248326,"remaining_time":5.46931806},
{"learn":[0.8351934142],"iteration":502,"passed_time":5.521808504,"remaining_time":5.455942001},
{"learn":[0.8350976754],"iteration":503,"passed_time":5.529207534,"remaining_time":5.441442335},
{"learn":[0.834998765],"iteration":504,"passed_time":5.53759474,"remaining_time":5.427939398},
{"learn":[0.8349624481],"iteration":505,"passed_time":5.544329237,"remaining_time":5.412843168},
{"learn":[0.8348946053],"iteration":506,"passed_time":5.553096751,"remaining_time":5.399756802},
{"learn":[0.8347886575],"iteration":507,"passed_time":5.56079429,"remaining_time":5.385651162},
{"learn":[0.8347183282],"iteration":508,"passed_time":5.570238387,"remaining_time":5.373255497},
{"learn":[0.8346776999],"iteration":509,"passed_time":5.577660379,"remaining_time":5.3589286},
{"learn":[0.8346146096],"iteration":510,"passed_time":5.585671482,"remaining_time":5.345192475},
{"learn":[0.8345567041],"iteration":511,"passed_time":5.593027439,"remaining_time":5.330854278},
{"learn":[0.834485713],"iteration":512,"passed_time":5.601971918,"remaining_time":5.318051314},
{"learn":[0.8344417498],"iteration":513,"passed_time":5.609685171,"remaining_time":5.304099208},
{"learn":[0.8343804996],"iteration":514,"passed_time":5.618376487,"remaining_time":5.29109242},
{"learn":[0.8343002865],"iteration":515,"passed_time":5.625594484,"remaining_time":5.276720407},
{"learn":[0.8342513041],"iteration":516,"passed_time":5.632927883,"remaining_time":5.262483883},
{"learn":[0.8341518169],"iteration":517,"passed_time":5.640493483,"remaining_time":5.248490075},
{"learn":[0.8340715684],"iteration":518,"passed_time":5.650708638,"remaining_time":5.236976599},
{"learn":[0.8340221039],"iteration":519,"passed_time":5.658227701,"remaining_time":5.222979416},
{"learn":[0.8339386368],"iteration":520,"passed_time":5.667897042,"remaining_time":5.210984037},
{"learn":[0.8338820442],"iteration":521,"passed_time":5.675134302,"remaining_time":5.196770491},
{"learn":[0.8338250518],"iteration":522,"passed_time":5.684309116,"remaining_time":5.184350762},
{"learn":[0.8337790328],"iteration":523,"passed_time":5.692491247,"remaining_time":5.171041667},
{"learn":[0.833697857],"iteration":524,"passed_time":5.701913422,"remaining_time":5.158874048},
{"learn":[0.8336369609],"iteration":525,"passed_time":5.710020917,"remaining_time":5.145532157},
{"learn":[0.8335631336],"iteration":526,"passed_time":5.717927359,"remaining_time":5.132029679},
{"learn":[0.8334802059],"iteration":527,"passed_time":5.726067735,"remaining_time":5.11875752},
{"learn":[0.8333958079],"iteration":528,"passed_time":5.734503937,"remaining_time":5.105768156},
{"learn":[0.8333211947],"iteration":529,"passed_time":5.74287456,"remaining_time":5.092737818},
{"learn":[0.8332442515],"iteration":530,"passed_time":5.752079783,"remaining_time":5.080462181},
{"learn":[0.8331829636],"iteration":531,"passed_time":5.760167622,"remaining_time":5.067215126},
{"learn":[0.8331128429],"iteration":532,"passed_time":5.767847745,"remaining_time":5.053630201},
{"learn":[0.8330004508],"iteration":533,"passed_time":5.776103374,"remaining_time":5.040569611},
{"learn":[0.832937911],"iteration":534,"passed_time":5.784311484,"remaining_time":5.027485682},
{"learn":[0.8328341413],"iteration":535,"passed_time":5.794142368,"remaining_time":5.015824736},
{"learn":[0.8327702877],"iteration":536,"passed_time":5.801985643,"remaining_time":5.002456895},
{"learn":[0.8326942573],"iteration":537,"passed_time":5.810615907,"remaining_time":4.989785407},
{"learn":[0.8326316254],"iteration":538,"passed_time":5.818287788,"remaining_time":4.976309221},
{"learn":[0.8325663374],"iteration":539,"passed_time":5.825737518,"remaining_time":4.962665293},
{"learn":[0.8324363044],"iteration":540,"passed_time":5.833688302,"remaining_time":4.949469372},
{"learn":[0.8323312615],"iteration":541,"passed_time":5.842993404,"remaining_time":4.93743723},
{"learn":[0.8322447382],"iteration":542,"passed_time":5.851947347,"remaining_time":4.925119591},
{"learn":[0.8321324233],"iteration":543,"passed_time":5.861467801,"remaining_time":4.913289186},
{"learn":[0.8320436295],"iteration":544,"passed_time":5.869515984,"remaining_time":4.900238115},
{"learn":[0.8319958072],"iteration":545,"passed_time":5.878235519,"remaining_time":4.8877636},
{"learn":[0.8319388459],"iteration":546,"passed_time":5.885357583,"remaining_time":4.873979863},
{"learn":[0.8318647079],"iteration":547,"passed_time":5.894841129,"remaining_time":4.86216823},
{"learn":[0.8318094303],"iteration":548,"passed_time":5.902141523,"remaining_time":4.848571634},
{"learn":[0.8316940744],"iteration":549,"passed_time":5.911679313,"remaining_time":4.836828529},
{"learn":[0.8316542837],"iteration":550,"passed_time":5.919351062,"remaining_time":4.823572825},
{"learn":[0.8315803425],"iteration":551,"passed_time":5.929087229,"remaining_time":4.812012824},
{"learn":[0.8315349756],"iteration":552,"passed_time":5.94014107,"remaining_time":4.801524517},
{"learn":[0.8314584564],"iteration":553,"passed_time":5.948481365,"remaining_time":4.788849619},
{"learn":[0.8313264746],"iteration":554,"passed_time":5.95792421,"remaining_time":4.777074367},
{"learn":[0.8312171634],"iteration":555,"passed_time":5.96563477,"remaining_time":4.763924169},
{"learn":[0.8311529877],"iteration":556,"passed_time":5.973475204,"remaining_time":4.750896796},
{"learn":[0.831055417],"iteration":557,"passed_time":5.981368676,"remaining_time":4.737930027},
{"learn":[0.8309748714],"iteration":558,"passed_time":5.990494483,"remaining_time":4.725953609},
{"learn":[0.8308654178],"iteration":559,"passed_time":5.998302599,"remaining_time":4.712952042},
{"learn":[0.8307708873],"iteration":560,"passed_time":6.007341939,"remaining_time":4.700932462},
{"learn":[0.8307168604],"iteration":561,"passed_time":6.015487636,"remaining_time":4.688227019},
{"learn":[0.8305711051],"iteration":562,"passed_time":6.023294603,"remaining_time":4.675274851},
{"learn":[0.8304976479],"iteration":563,"passed_time":6.031201955,"remaining_time":4.662418532},
{"learn":[0.8304436212],"iteration":564,"passed_time":6.041485649,"remaining_time":4.651409305},
{"learn":[0.8303516963],"iteration":565,"passed_time":6.049590044,"remaining_time":4.638731589},
{"learn":[0.8302870727],"iteration":566,"passed_time":6.057612565,"remaining_time":4.626007479},
{"learn":[0.8302352116],"iteration":567,"passed_time":6.064670949,"remaining_time":4.612566638},
{"learn":[0.8301807362],"iteration":568,"passed_time":6.072798302,"remaining_time":4.59995794},
{"learn":[0.8300904714],"iteration":569,"passed_time":6.081320753,"remaining_time":4.587663024},
{"learn":[0.8299828634],"iteration":570,"passed_time":6.090670112,"remaining_time":4.576002589},
{"learn":[0.8299235039],"iteration":571,"passed_time":6.100078047,"remaining_time":4.564394063},
{"learn":[0.8298427062],"iteration":572,"passed_time":6.107636904,"remaining_time":4.551415284},
{"learn":[0.8297692642],"iteration":573,"passed_time":6.115494707,"remaining_time":4.538677256},
{"learn":[0.8296466222],"iteration":574,"passed_time":6.123569216,"remaining_time":4.526116377},
{"learn":[0.8295923585],"iteration":575,"passed_time":6.13233517,"remaining_time":4.514080056},
{"learn":[0.8294744074],"iteration":576,"passed_time":6.140707765,"remaining_time":4.501766698},
{"learn":[0.8293560585],"iteration":577,"passed_time":6.150191704,"remaining_time":4.490278372},
{"learn":[0.8292790672],"iteration":578,"passed_time":6.157532439,"remaining_time":4.477238613},
{"learn":[0.8291709322],"iteration":579,"passed_time":6.165595284,"remaining_time":4.464741412},
{"learn":[0.8290960097],"iteration":580,"passed_time":6.173601665,"remaining_time":4.452218757},
{"learn":[0.8289989378],"iteration":581,"passed_time":6.184549053,"remaining_time":4.44182389},
{"learn":[0.828936017],"iteration":582,"passed_time":6.192508817,"remaining_time":4.429290183},
{"learn":[0.8288860141],"iteration":583,"passed_time":6.201963487,"remaining_time":4.417837004},
{"learn":[0.828842318],"iteration":584,"passed_time":6.212271918,"remaining_time":4.406996318},
{"learn":[0.8287747372],"iteration":585,"passed_time":6.220543833,"remaining_time":4.39471868},
{"learn":[0.8287243978],"iteration":586,"passed_time":6.230122251,"remaining_time":4.383373917},
{"learn":[0.8286445157],"iteration":587,"passed_time":6.238154005,"remaining_time":4.370951445},
{"learn":[0.8285758535],"iteration":588,"passed_time":6.246975922,"remaining_time":4.359095253},
{"learn":[0.8284825703],"iteration":589,"passed_time":6.256346352,"remaining_time":4.347630516},
{"learn":[0.8284334254],"iteration":590,"passed_time":6.265184597,"remaining_time":4.335804569},
{"learn":[0.828313469],"iteration":591,"passed_time":6.273346698,"remaining_time":4.323522725},
{"learn":[0.8282391712],"iteration":592,"passed_time":6.282979529,"remaining_time":4.312264196},
{"learn":[0.8281457819],"iteration":593,"passed_time":6.292059414,"remaining_time":4.300633202},
{"learn":[0.8280557858],"iteration":594,"passed_time":6.3001809,"remaining_time":4.288358428},
{"learn":[0.8279248512],"iteration":595,"passed_time":6.308445499,"remaining_time":4.2761946},
{"learn":[0.8278685909],"iteration":596,"passed_time":6.318010094,"remaining_time":4.264921387},
{"learn":[0.8278247693],"iteration":597,"passed_time":6.332127031,"remaining_time":4.256714158},
{"learn":[0.8277726694],"iteration":598,"passed_time":6.343592874,"remaining_time":4.246712425},
{"learn":[0.8277154573],"iteration":599,"passed_time":6.356872221,"remaining_time":4.237914814},
{"learn":[0.8276330136],"iteration":600,"passed_time":6.367890587,"remaining_time":4.227601238},
{"learn":[0.8275194118],"iteration":601,"passed_time":6.380870777,"remaining_time":4.218582341},
{"learn":[0.8274871334],"iteration":602,"passed_time":6.391588637,"remaining_time":4.208060844},
{"learn":[0.8274231683],"iteration":603,"passed_time":6.401093181,"remaining_time":4.196743211},
{"learn":[0.8273559183],"iteration":604,"passed_time":6.410540615,"remaining_time":4.185394286},
{"learn":[0.8272837632],"iteration":605,"passed_time":6.420496631,"remaining_time":4.174382298},
{"learn":[0.8272137872],"iteration":606,"passed_time":6.432275581,"remaining_time":4.164554042},
{"learn":[0.8271430876],"iteration":607,"passed_time":6.44968622,"remaining_time":4.158350326},
{"learn":[0.8270997762],"iteration":608,"passed_time":6.460090411,"remaining_time":4.147611413},
{"learn":[0.8270196874],"iteration":609,"passed_time":6.47338782,"remaining_time":4.13872336},
{"learn":[0.8268941076],"iteration":610,"passed_time":6.490917387,"remaining_time":4.132515325},
{"learn":[0.8268299233],"iteration":611,"passed_time":6.503881713,"remaining_time":4.123375988},
{"learn":[0.8267135543],"iteration":612,"passed_time":6.51526699,"remaining_time":4.113227284},
{"learn":[0.8266474568],"iteration":613,"passed_time":6.527568233,"remaining_time":4.103650387},
{"learn":[0.8265873163],"iteration":614,"passed_time":6.538569281,"remaining_time":4.093250688},
{"learn":[0.8265083388],"iteration":615,"passed_time":6.550714469,"remaining_time":4.083562266},
{"learn":[0.826457406],"iteration":616,"passed_time":6.561449989,"remaining_time":4.072990836},
{"learn":[0.8264034833],"iteration":617,"passed_time":6.575688525,"remaining_time":4.064584169},
{"learn":[0.8263454586],"iteration":618,"passed_time":6.587442313,"remaining_time":4.054629275},
{"learn":[0.8262478326],"iteration":619,"passed_time":6.597558467,"remaining_time":4.043664867},
{"learn":[0.8261851773],"iteration":620,"passed_time":6.609265208,"remaining_time":4.033673935},
{"learn":[0.8261008848],"iteration":621,"passed_time":6.624246489,"remaining_time":4.02566748},
{"learn":[0.826054597],"iteration":622,"passed_time":6.634598428,"remaining_time":4.014837251},
{"learn":[0.8260223188],"iteration":623,"passed_time":6.643383055,"remaining_time":4.003064148},
{"learn":[0.8259513631],"iteration":624,"passed_time":6.657677844,"remaining_time":3.994606707},
{"learn":[0.8258846097],"iteration":625,"passed_time":6.669635005,"remaining_time":3.984734013},
{"learn":[0.8258286399],"iteration":626,"passed_time":6.678561754,"remaining_time":3.973051889},
{"learn":[0.8257808821],"iteration":627,"passed_time":6.688419151,"remaining_time":3.961929815},
{"learn":[0.8256360481],"iteration":628,"passed_time":6.699156228,"remaining_time":3.951330621},
{"learn":[0.8255255935],"iteration":629,"passed_time":6.709345571,"remaining_time":3.940409304},
{"learn":[0.8254099527],"iteration":630,"passed_time":6.721082779,"remaining_time":3.930395476},
{"learn":[0.8253176402],"iteration":631,"passed_time":6.732312448,"remaining_time":3.920080666},
{"learn":[0.8252779642],"iteration":632,"passed_time":6.74177999,"remaining_time":3.908741321},
{"learn":[0.8252351421],"iteration":633,"passed_time":6.750541901,"remaining_time":3.89700053},
{"learn":[0.8251270255],"iteration":634,"passed_time":6.762124208,"remaining_time":3.886890293},
{"learn":[0.8250386495],"iteration":635,"passed_time":6.772947131,"remaining_time":3.876340811},
{"learn":[0.8249622791],"iteration":636,"passed_time":6.782923368,"remaining_time":3.865307979},
{"learn":[0.8248884967],"iteration":637,"passed_time":6.790863693,"remaining_time":3.853123287},
{"learn":[0.8248162525],"iteration":638,"passed_time":6.799545988,"remaining_time":3.841371051},
{"learn":[0.8247680779],"iteration":639,"passed_time":6.807595293,"remaining_time":3.829272352},
{"learn":[0.8246823911],"iteration":640,"passed_time":6.820192945,"remaining_time":3.819733646},
{"learn":[0.82463146],"iteration":641,"passed_time":6.830593786,"remaining_time":3.808960398},
{"learn":[0.8245760925],"iteration":642,"passed_time":6.839177814,"remaining_time":3.797179595},
{"learn":[0.824475217],"iteration":643,"passed_time":6.848154483,"remaining_time":3.78562577},
{"learn":[0.8243521778],"iteration":644,"passed_time":6.857274047,"remaining_time":3.774158584},
{"learn":[0.8243029106],"iteration":645,"passed_time":6.868678215,"remaining_time":3.763950601},
{"learn":[0.8242466369],"iteration":646,"passed_time":6.878777879,"remaining_time":3.753027189},
{"learn":[0.824185525],"iteration":647,"passed_time":6.886877612,"remaining_time":3.741019937},
{"learn":[0.8241374735],"iteration":648,"passed_time":6.896068137,"remaining_time":3.729614663},
{"learn":[0.824090158],"iteration":649,"passed_time":6.904438028,"remaining_time":3.717774323},
{"learn":[0.8239937797],"iteration":650,"passed_time":6.914634141,"remaining_time":3.706923679},
{"learn":[0.8239630074],"iteration":651,"passed_time":6.923834543,"remaining_time":3.69554359},
{"learn":[0.8238239531],"iteration":652,"passed_time":6.93306695,"remaining_time":3.684187185},
{"learn":[0.8237853313],"iteration":653,"passed_time":6.942335888,"remaining_time":3.672856601},
{"learn":[0.8236895472],"iteration":654,"passed_time":6.951979788,"remaining_time":3.661729812},
{"learn":[0.8236374854],"iteration":655,"passed_time":6.962640502,"remaining_time":3.651140751},
{"learn":[0.8235183144],"iteration":656,"passed_time":6.970752575,"remaining_time":3.639220903},
{"learn":[0.8234530275],"iteration":657,"passed_time":6.979954812,"remaining_time":3.627879249},
{"learn":[0.8233590845],"iteration":658,"passed_time":6.988939634,"remaining_time":3.616431586},
{"learn":[0.8233089057],"iteration":659,"passed_time":6.997551078,"remaining_time":3.60479904},
{"learn":[0.8231995343],"iteration":660,"passed_time":7.007553268,"remaining_time":3.593888892},
{"learn":[0.8230867524],"iteration":661,"passed_time":7.015839782,"remaining_time":3.582105508},
{"learn":[0.823028404],"iteration":662,"passed_time":7.024949599,"remaining_time":3.570751153},
{"learn":[0.8229687709],"iteration":663,"passed_time":7.032866099,"remaining_time":3.558799713},
{"learn":[0.8229169872],"iteration":664,"passed_time":7.041391323,"remaining_time":3.547167057},
{"learn":[0.8228579234],"iteration":665,"passed_time":7.049633951,"remaining_time":3.535402011},
{"learn":[0.8227843119],"iteration":666,"passed_time":7.060966902,"remaining_time":3.525190372},
{"learn":[0.8227071779],"iteration":667,"passed_time":7.069481796,"remaining_time":3.513574785},
{"learn":[0.8226425785],"iteration":668,"passed_time":7.077955395,"remaining_time":3.501948035},
{"learn":[0.8225179673],"iteration":669,"passed_time":7.086738156,"remaining_time":3.490482972},
{"learn":[0.8224397806],"iteration":670,"passed_time":7.09516396,"remaining_time":3.478850884},
{"learn":[0.8223254513],"iteration":671,"passed_time":7.105135716,"remaining_time":3.467982909},
{"learn":[0.8222602512],"iteration":672,"passed_time":7.113468313,"remaining_time":3.456321157},
{"learn":[0.8222098826],"iteration":673,"passed_time":7.122901899,"remaining_time":3.445201809},
{"learn":[0.8220762763],"iteration":674,"passed_time":7.131596292,"remaining_time":3.433731548},
{"learn":[0.8220030406],"iteration":675,"passed_time":7.140315494,"remaining_time":3.42228139},
{"learn":[0.8219182943],"iteration":676,"passed_time":7.149850485,"remaining_time":3.411228518},
{"learn":[0.8218500493],"iteration":677,"passed_time":7.159770429,"remaining_time":3.400362947},
{"learn":[0.8217885983],"iteration":678,"passed_time":7.17034367,"remaining_time":3.389809011},
{"learn":[0.821701766],"iteration":679,"passed_time":7.178168101,"remaining_time":3.377961459},
{"learn":[0.8216231605],"iteration":680,"passed_time":7.186441725,"remaining_time":3.366336138},
{"learn":[0.8215106176],"iteration":681,"passed_time":7.195757465,"remaining_time":3.35520656},
{"learn":[0.821455013],"iteration":682,"passed_time":7.206863608,"remaining_time":3.34491327},
{"learn":[0.8213470707],"iteration":683,"passed_time":7.216051709,"remaining_time":3.333731491},
{"learn":[0.8212867353],"iteration":684,"passed_time":7.224707688,"remaining_time":3.322310835},
{"learn":[0.8212494591],"iteration":685,"passed_time":7.234305837,"remaining_time":3.311329494},
{"learn":[0.8212169249],"iteration":686,"passed_time":7.245093273,"remaining_time":3.300894024},
{"learn":[0.8211421253],"iteration":687,"passed_time":7.256270658,"remaining_time":3.290634368},
{"learn":[0.821055971],"iteration":688,"passed_time":7.266160758,"remaining_time":3.279790995},
{"learn":[0.8209638457],"iteration":689,"passed_time":7.274030348,"remaining_time":3.26804262},
{"learn":[0.8208542055],"iteration":690,"passed_time":7.282533091,"remaining_time":3.256588604},
{"learn":[0.820813646],"iteration":691,"passed_time":7.29179447,"remaining_time":3.245480776},
{"learn":[0.8207329322],"iteration":692,"passed_time":7.301160822,"remaining_time":3.23442478},
{"learn":[0.8206361848],"iteration":693,"passed_time":7.308733737,"remaining_time":3.222582887},
{"learn":[0.8205119516],"iteration":694,"passed_time":7.317307886,"remaining_time":3.21119267},
{"learn":[0.8204268982],"iteration":695,"passed_time":7.3259153,"remaining_time":3.199825074},
{"learn":[0.8203850436],"iteration":696,"passed_time":7.333374993,"remaining_time":3.18796646},
{"learn":[0.820325693],"iteration":697,"passed_time":7.341353386,"remaining_time":3.176344875},
{"learn":[0.8202919651],"iteration":698,"passed_time":7.350426064,"remaining_time":3.165204929},
{"learn":[0.8202378877],"iteration":699,"passed_time":7.36101149,"remaining_time":3.15471921},
{"learn":[0.8201838132],"iteration":700,"passed_time":7.368628974,"remaining_time":3.14296728},
{"learn":[0.8201236464],"iteration":701,"passed_time":7.376408535,"remaining_time":3.131295931},
{"learn":[0.8200727521],"iteration":702,"passed_time":7.383674893,"remaining_time":3.119418838},
{"learn":[0.8200086695],"iteration":703,"passed_time":7.392859378,"remaining_time":3.10836133},
{"learn":[0.8199538694],"iteration":704,"passed_time":7.401215178,"remaining_time":3.09696238},
{"learn":[0.8198910433],"iteration":705,"passed_time":7.410136929,"remaining_time":3.08580773},
{"learn":[0.8198246539],"iteration":706,"passed_time":7.41898365,"remaining_time":3.074628302},
{"learn":[0.8197603768],"iteration":707,"passed_time":7.42695664,"remaining_time":3.063095111},
{"learn":[0.8196754062],"iteration":708,"passed_time":7.434820613,"remaining_time":3.051527219},
{"learn":[0.8196055174],"iteration":709,"passed_time":7.443858431,"remaining_time":3.040449218},
{"learn":[0.819518285],"iteration":710,"passed_time":7.452084601,"remaining_time":3.029047046},
{"learn":[0.8194155635],"iteration":711,"passed_time":7.461335194,"remaining_time":3.018068168},
{"learn":[0.819336394],"iteration":712,"passed_time":7.469183577,"remaining_time":3.006529715},
{"learn":[0.8192362706],"iteration":713,"passed_time":7.479202485,"remaining_time":2.995871023},
{"learn":[0.8191721727],"iteration":714,"passed_time":7.48720835,"remaining_time":2.98441172},
{"learn":[0.819109831],"iteration":715,"passed_time":7.496015778,"remaining_time":2.973280001},
{"learn":[0.8189952155],"iteration":716,"passed_time":7.504440369,"remaining_time":2.96200366},
{"learn":[0.8189232093],"iteration":717,"passed_time":7.512420959,"remaining_time":2.950560878},
{"learn":[0.8188519908],"iteration":718,"passed_time":7.521491389,"remaining_time":2.939553658},
{"learn":[0.818792166],"iteration":719,"passed_time":7.530961713,"remaining_time":2.928707333},
{"learn":[0.8187075814],"iteration":720,"passed_time":7.540842368,"remaining_time":2.918023607},
{"learn":[0.818620247],"iteration":721,"passed_time":7.549754052,"remaining_time":2.906969012},
{"learn":[0.8185457596],"iteration":722,"passed_time":7.559575497,"remaining_time":2.896268897},
{"learn":[0.8184136758],"iteration":723,"passed_time":7.574285844,"remaining_time":2.887434935},
{"learn":[0.8183899441],"iteration":724,"passed_time":7.582819234,"remaining_time":2.876241778},
{"learn":[0.8183383961],"iteration":725,"passed_time":7.59602075,"remaining_time":2.866817749},
{"learn":[0.8182728743],"iteration":726,"passed_time":7.606596722,"remaining_time":2.856397394},
{"learn":[0.8182005221],"iteration":727,"passed_time":7.615795129,"remaining_time":2.845461916},
{"learn":[0.8181169469],"iteration":728,"passed_time":7.623587537,"remaining_time":2.834008536},
{"learn":[0.818043282],"iteration":729,"passed_time":7.631562357,"remaining_time":2.822632653},
{"learn":[0.8179861057],"iteration":730,"passed_time":7.641371576,"remaining_time":2.811941113},
{"learn":[0.8179160639],"iteration":731,"passed_time":7.651174261,"remaining_time":2.801249593},
{"learn":[0.8178557456],"iteration":732,"passed_time":7.658559406,"remaining_time":2.789679893},
{"learn":[0.8178025007],"iteration":733,"passed_time":7.667807402,"remaining_time":2.778796688},
{"learn":[0.8177490608],"iteration":734,"passed_time":7.675722377,"remaining_time":2.76743732},
{"learn":[0.8176981244],"iteration":735,"passed_time":7.685080219,"remaining_time":2.756604861},
{"learn":[0.8176499761],"iteration":736,"passed_time":7.692658739,"remaining_time":2.745141449},
{"learn":[0.8176177897],"iteration":737,"passed_time":7.701771353,"remaining_time":2.734233191},
{"learn":[0.8175387494],"iteration":738,"passed_time":7.710543434,"remaining_time":2.723209521},
{"learn":[0.8174426093],"iteration":739,"passed_time":7.718949895,"remaining_time":2.712063476},
{"learn":[0.8173529307],"iteration":740,"passed_time":7.726124577,"remaining_time":2.700494285},
{"learn":[0.8173112238],"iteration":741,"passed_time":7.735873041,"remaining_time":2.689831866},
{"learn":[0.8172437052],"iteration":742,"passed_time":7.743515853,"remaining_time":2.678443572},
{"learn":[0.8171918059],"iteration":743,"passed_time":7.752376683,"remaining_time":2.66748445},
{"learn":[0.8171313378],"iteration":744,"passed_time":7.760038564,"remaining_time":2.656120582},
{"learn":[0.8170882134],"iteration":745,"passed_time":7.767827878,"remaining_time":2.644810028},
{"learn":[0.8169793853],"iteration":746,"passed_time":7.776781156,"remaining_time":2.633903122},
{"learn":[0.816873682],"iteration":747,"passed_time":7.786243255,"remaining_time":2.623172861},
{"learn":[0.8167952082],"iteration":748,"passed_time":7.794741989,"remaining_time":2.61212315},
{"learn":[0.8167512593],"iteration":749,"passed_time":7.803956459,"remaining_time":2.60131882},
{"learn":[0.8166755633],"iteration":750,"passed_time":7.812850785,"remaining_time":2.590412577},
{"learn":[0.8166052893],"iteration":751,"passed_time":7.820380663,"remaining_time":2.579061708},
{"learn":[0.8165243997],"iteration":752,"passed_time":7.830214976,"remaining_time":2.568476891},
{"learn":[0.8164534888],"iteration":753,"passed_time":7.837877089,"remaining_time":2.557185363},
{"learn":[0.816420779],"iteration":754,"passed_time":7.846602691,"remaining_time":2.546248555},
{"learn":[0.8163556247],"iteration":755,"passed_time":7.854155203,"remaining_time":2.534938981},
{"learn":[0.8162749214],"iteration":756,"passed_time":7.862982163,"remaining_time":2.524048435},
{"learn":[0.8161891544],"iteration":757,"passed_time":7.870788178,"remaining_time":2.512837387},
{"learn":[0.8160765572],"iteration":758,"passed_time":7.88034899,"remaining_time":2.502192499},
{"learn":[0.8159780445],"iteration":759,"passed_time":7.888375087,"remaining_time":2.491065817},
{"learn":[0.8158720701],"iteration":760,"passed_time":7.897850912,"remaining_time":2.480402586},
{"learn":[0.8157720255],"iteration":761,"passed_time":7.906860422,"remaining_time":2.469596825},
{"learn":[0.815694207],"iteration":762,"passed_time":7.914685007,"remaining_time":2.458427715},
{"learn":[0.8156585781],"iteration":763,"passed_time":7.921954817,"remaining_time":2.44709599},
{"learn":[0.8155882321],"iteration":764,"passed_time":7.931399645,"remaining_time":2.436443028},
{"learn":[0.8155072834],"iteration":765,"passed_time":7.941704018,"remaining_time":2.426055797},
{"learn":[0.8154284722],"iteration":766,"passed_time":7.949487697,"remaining_time":2.414903042},
{"learn":[0.8153893382],"iteration":767,"passed_time":7.957426893,"remaining_time":2.403806041},
{"learn":[0.8153140653],"iteration":768,"passed_time":7.965517007,"remaining_time":2.392762586},
{"learn":[0.8152429847],"iteration":769,"passed_time":7.974737003,"remaining_time":2.3820643},
{"learn":[0.8151515945],"iteration":770,"passed_time":7.98270342,"remaining_time":2.370997514},
{"learn":[0.8150881501],"iteration":771,"passed_time":7.993612185,"remaining_time":2.360807744},
{"learn":[0.8150572104],"iteration":772,"passed_time":8.001332926,"remaining_time":2.349679915},
{"learn":[0.8150237178],"iteration":773,"passed_time":8.009800697,"remaining_time":2.338779015},
{"learn":[0.8149436392],"iteration":774,"passed_time":8.017673992,"remaining_time":2.327711804},
{"learn":[0.8148437076],"iteration":775,"passed_time":8.027634615,"remaining_time":2.317255353},
{"learn":[0.8147486855],"iteration":776,"passed_time":8.037256545,"remaining_time":2.306702972},
{"learn":[0.8146987515],"iteration":777,"passed_time":8.046335301,"remaining_time":2.295997991},
{"learn":[0.8146439171],"iteration":778,"passed_time":8.054257541,"remaining_time":2.284969084},
{"learn":[0.8145596213],"iteration":779,"passed_time":8.062019698,"remaining_time":2.273902992},
{"learn":[0.814513119],"iteration":780,"passed_time":8.070965414,"remaining_time":2.263177241},
{"learn":[0.8144376454],"iteration":781,"passed_time":8.079003421,"remaining_time":2.252203},
{"learn":[0.8143397059],"iteration":782,"passed_time":8.088128131,"remaining_time":2.241537426},
{"learn":[0.8142554838],"iteration":783,"passed_time":8.096099025,"remaining_time":2.230557895},
{"learn":[0.8141997465],"iteration":784,"passed_time":8.104066926,"remaining_time":2.219585209},
{"learn":[0.8141324447],"iteration":785,"passed_time":8.111421028,"remaining_time":2.208453053},
{"learn":[0.8140574009],"iteration":786,"passed_time":8.120893514,"remaining_time":2.197903836},
{"learn":[0.8139620336],"iteration":787,"passed_time":8.12866712,"remaining_time":2.186900291},
{"learn":[0.8138804403],"iteration":788,"passed_time":8.137762513,"remaining_time":2.176258416},
{"learn":[0.8137853317],"iteration":789,"passed_time":8.145176328,"remaining_time":2.165173454},
{"learn":[0.8137146996],"iteration":790,"passed_time":8.154080478,"remaining_time":2.154491555},
{"learn":[0.8136121319],"iteration":791,"passed_time":8.163106403,"remaining_time":2.143846126},
{"learn":[0.8135320491],"iteration":792,"passed_time":8.172774724,"remaining_time":2.133372469},
{"learn":[0.8134557857],"iteration":793,"passed_time":8.18127872,"remaining_time":2.122598761},
{"learn":[0.8133440274],"iteration":794,"passed_time":8.189876917,"remaining_time":2.111855054},
{"learn":[0.8132366888],"iteration":795,"passed_time":8.198473675,"remaining_time":2.101116369},
{"learn":[0.8131446099],"iteration":796,"passed_time":8.207000755,"remaining_time":2.090365311},
{"learn":[0.8130796375],"iteration":797,"passed_time":8.217104849,"remaining_time":2.080019022},
{"learn":[0.8130251301],"iteration":798,"passed_time":8.225308848,"remaining_time":2.069195342},
{"learn":[0.8129426372],"iteration":799,"passed_time":8.235275278,"remaining_time":2.05881882},
{"learn":[0.8128381964],"iteration":800,"passed_time":8.242667044,"remaining_time":2.047803673},
{"learn":[0.8127567834],"iteration":801,"passed_time":8.250663091,"remaining_time":2.036946748},
{"learn":[0.8127114009],"iteration":802,"passed_time":8.257911567,"remaining_time":2.025913548},
{"learn":[0.8126758193],"iteration":803,"passed_time":8.268140773,"remaining_time":2.015616407},
{"learn":[0.8125627112],"iteration":804,"passed_time":8.276207151,"remaining_time":2.004795521},
{"learn":[0.8124966656],"iteration":805,"passed_time":8.285485123,"remaining_time":1.994273094},
{"learn":[0.8123984337],"iteration":806,"passed_time":8.29287488,"remaining_time":1.983302171},
{"learn":[0.812364109],"iteration":807,"passed_time":8.300851926,"remaining_time":1.972479666},
{"learn":[0.8123021183],"iteration":808,"passed_time":8.307933493,"remaining_time":1.961452778},
{"learn":[0.8122126445],"iteration":809,"passed_time":8.317907288,"remaining_time":1.951114055},
{"learn":[0.8121338599],"iteration":810,"passed_time":8.325835605,"remaining_time":1.940299543},
{"learn":[0.812100143],"iteration":811,"passed_time":8.333808022,"remaining_time":1.92950235},
{"learn":[0.8120433396],"iteration":812,"passed_time":8.341549069,"remaining_time":1.918658888},
{"learn":[0.8119595535],"iteration":813,"passed_time":8.349545059,"remaining_time":1.907881303},
{"learn":[0.8118506893],"iteration":814,"passed_time":8.35704435,"remaining_time":1.896997797},
{"learn":[0.8117865222],"iteration":815,"passed_time":8.366839875,"remaining_time":1.886640364},
{"learn":[0.8116970404],"iteration":816,"passed_time":8.37556198,"remaining_time":1.876043871},
{"learn":[0.8116346572],"iteration":817,"passed_time":8.383875946,"remaining_time":1.865361152},
{"learn":[0.8115473651],"iteration":818,"passed_time":8.391857511,"remaining_time":1.854610756},
{"learn":[0.8114955551],"iteration":819,"passed_time":8.39940617,"remaining_time":1.843772086},
{"learn":[0.8114011972],"iteration":820,"passed_time":8.407263151,"remaining_time":1.833008653},
{"learn":[0.8113500222],"iteration":821,"passed_time":8.415973551,"remaining_time":1.822437095},
{"learn":[0.8112455953],"iteration":822,"passed_time":8.425157747,"remaining_time":1.811971958},
{"learn":[0.8111363431],"iteration":823,"passed_time":8.434134103,"remaining_time":1.801465537},
{"learn":[0.8110770511],"iteration":824,"passed_time":8.442348399,"remaining_time":1.790801176},
{"learn":[0.8109658112],"iteration":825,"passed_time":8.450995626,"remaining_time":1.780233945},
{"learn":[0.8109068835],"iteration":826,"passed_time":8.460193382,"remaining_time":1.769786524},
{"learn":[0.8108160704],"iteration":827,"passed_time":8.468080427,"remaining_time":1.759069847},
{"learn":[0.810779248],"iteration":828,"passed_time":8.476861474,"remaining_time":1.748544405},
{"learn":[0.8106933498],"iteration":829,"passed_time":8.483911194,"remaining_time":1.737668558},
{"learn":[0.8106194977],"iteration":830,"passed_time":8.494070457,"remaining_time":1.727434305},
{"learn":[0.8105245419],"iteration":831,"passed_time":8.502795989,"remaining_time":1.716910729},
{"learn":[0.8104456805],"iteration":832,"passed_time":8.513119528,"remaining_time":1.706711838},
{"learn":[0.8103940017],"iteration":833,"passed_time":8.52233749,"remaining_time":1.696292594},
{"learn":[0.8102995984],"iteration":834,"passed_time":8.530666052,"remaining_time":1.685700477},
{"learn":[0.8102214347],"iteration":835,"passed_time":8.538580896,"remaining_time":1.675032616},
{"learn":[0.8101422969],"iteration":836,"passed_time":8.545978986,"remaining_time":1.664270699},
{"learn":[0.8100611499],"iteration":837,"passed_time":8.554506489,"remaining_time":1.653735145},
{"learn":[0.8100135071],"iteration":838,"passed_time":8.562440246,"remaining_time":1.643090441},
{"learn":[0.8099138744],"iteration":839,"passed_time":8.571244961,"remaining_time":1.632618088},
{"learn":[0.8098558658],"iteration":840,"passed_time":8.579823916,"remaining_time":1.622107019},
{"learn":[0.8098161602],"iteration":841,"passed_time":8.588433517,"remaining_time":1.611606289},
{"learn":[0.8097812196],"iteration":842,"passed_time":8.595385678,"remaining_time":1.600801366},
{"learn":[0.8096914496],"iteration":843,"passed_time":8.605991769,"remaining_time":1.590680943},
{"learn":[0.8096294558],"iteration":844,"passed_time":8.613693973,"remaining_time":1.580026705},
{"learn":[0.8095652567],"iteration":845,"passed_time":8.623363016,"remaining_time":1.569737476},
{"learn":[0.8095203578],"iteration":846,"passed_time":8.632063423,"remaining_time":1.559274739},
{"learn":[0.8094483335],"iteration":847,"passed_time":8.640098519,"remaining_time":1.548696904},
{"learn":[0.8093602782],"iteration":848,"passed_time":8.64887931,"remaining_time":1.538257687},
{"learn":[0.8093196882],"iteration":849,"passed_time":8.658099615,"remaining_time":1.527899932},
{"learn":[0.8092710793],"iteration":850,"passed_time":8.666719498,"remaining_time":1.517439724},
{"learn":[0.8092258738],"iteration":851,"passed_time":8.67444125,"remaining_time":1.506827823},
{"learn":[0.8091359413],"iteration":852,"passed_time":8.682284863,"remaining_time":1.496243698},
{"learn":[0.8090346321],"iteration":853,"passed_time":8.6901913,"remaining_time":1.485676733},
{"learn":[0.8089723415],"iteration":854,"passed_time":8.697757515,"remaining_time":1.475058292},
{"learn":[0.8089287254],"iteration":855,"passed_time":8.706621683,"remaining_time":1.46466533},
{"learn":[0.8088590425],"iteration":856,"passed_time":8.716374368,"remaining_time":1.454424194},
{"learn":[0.8088050114],"iteration":857,"passed_time":8.724806882,"remaining_time":1.443965708},
{"learn":[0.8087470356],"iteration":858,"passed_time":8.733134622,"remaining_time":1.43349474},
{"learn":[0.8086514939],"iteration":859,"passed_time":8.740952391,"remaining_time":1.422945738},
{"learn":[0.8085679794],"iteration":860,"passed_time":8.751284996,"remaining_time":1.412809076},
{"learn":[0.808477994],"iteration":861,"passed_time":8.759143157,"remaining_time":1.402275819},
{"learn":[0.8084209635],"iteration":862,"passed_time":8.768264887,"remaining_time":1.39194935},
{"learn":[0.8083901288],"iteration":863,"passed_time":8.77646756,"remaining_time":1.381481005},
{"learn":[0.8083016369],"iteration":864,"passed_time":8.784757872,"remaining_time":1.371031575},
{"learn":[0.8082348026],"iteration":865,"passed_time":8.792616132,"remaining_time":1.360520279},
{"learn":[0.8081899026],"iteration":866,"passed_time":8.801763846,"remaining_time":1.350212908},
{"learn":[0.8081285519],"iteration":867,"passed_time":8.809850187,"remaining_time":1.339746803},
{"learn":[0.8080091584],"iteration":868,"passed_time":8.817996351,"remaining_time":1.329295192},
{"learn":[0.8079194991],"iteration":869,"passed_time":8.826431939,"remaining_time":1.318892129},
{"learn":[0.8078590714],"iteration":870,"passed_time":8.834303899,"remaining_time":1.308410107},
{"learn":[0.8077936198],"iteration":871,"passed_time":8.844181269,"remaining_time":1.298228443},
{"learn":[0.8077346391],"iteration":872,"passed_time":8.854547939,"remaining_time":1.288118658},
{"learn":[0.8076629497],"iteration":873,"passed_time":8.863471041,"remaining_time":1.277800173},
{"learn":[0.8076015583],"iteration":874,"passed_time":8.871044619,"remaining_time":1.267292088},
{"learn":[0.8074903723],"iteration":875,"passed_time":8.879154234,"remaining_time":1.256866581},
{"learn":[0.8073913629],"iteration":876,"passed_time":8.886798885,"remaining_time":1.246381144},
{"learn":[0.807302031],"iteration":877,"passed_time":8.897200674,"remaining_time":1.236285287},
{"learn":[0.8072520115],"iteration":878,"passed_time":8.905554899,"remaining_time":1.225906875},
{"learn":[0.8071703057],"iteration":879,"passed_time":8.913733512,"remaining_time":1.215509115},
{"learn":[0.8070591732],"iteration":880,"passed_time":8.922506961,"remaining_time":1.205196741},
{"learn":[0.806966319],"iteration":881,"passed_time":8.930458307,"remaining_time":1.194777869},
{"learn":[0.8069197982],"iteration":882,"passed_time":8.938523775,"remaining_time":1.184379707},
{"learn":[0.8068678923],"iteration":883,"passed_time":8.94764895,"remaining_time":1.17412588},
{"learn":[0.8068145501],"iteration":884,"passed_time":8.956038256,"remaining_time":1.163778982},
{"learn":[0.8067378157],"iteration":885,"passed_time":8.965553373,"remaining_time":1.153581359},
{"learn":[0.8066689016],"iteration":886,"passed_time":8.973235296,"remaining_time":1.143151734},
{"learn":[0.8066453696],"iteration":887,"passed_time":8.980366861,"remaining_time":1.132658883},
{"learn":[0.8065733233],"iteration":888,"passed_time":8.989366454,"remaining_time":1.122406835},
{"learn":[0.8064879406],"iteration":889,"passed_time":8.997684976,"remaining_time":1.112073424},
{"learn":[0.8064032734],"iteration":890,"passed_time":9.008534453,"remaining_time":1.102054159},
{"learn":[0.8063379994],"iteration":891,"passed_time":9.016337688,"remaining_time":1.091664204},
{"learn":[0.8062779109],"iteration":892,"passed_time":9.025084496,"remaining_time":1.081393103},
{"learn":[0.8061923517],"iteration":893,"passed_time":9.032850517,"remaining_time":1.071009122},
{"learn":[0.8061436882],"iteration":894,"passed_time":9.042546592,"remaining_time":1.060857421},
{"learn":[0.8060831794],"iteration":895,"passed_time":9.050013093,"remaining_time":1.050447948},
{"learn":[0.8060175641],"iteration":896,"passed_time":9.058756597,"remaining_time":1.040191672},
{"learn":[0.8059649526],"iteration":897,"passed_time":9.066312006,"remaining_time":1.029803814},
{"learn":[0.8058810763],"iteration":898,"passed_time":9.075062154,"remaining_time":1.019556482},
{"learn":[0.8058595106],"iteration":899,"passed_time":9.082884427,"remaining_time":1.009209381},
{"learn":[0.8057965028],"iteration":900,"passed_time":9.091949983,"remaining_time":0.9990044931},
{"learn":[0.8057344438],"iteration":901,"passed_time":9.100300319,"remaining_time":0.9887244249},
{"learn":[0.8056769448],"iteration":902,"passed_time":9.108190117,"remaining_time":0.9783991598},
{"learn":[0.805593742],"iteration":903,"passed_time":9.116211645,"remaining_time":0.9680932721},
{"learn":[0.8055385586],"iteration":904,"passed_time":9.123707614,"remaining_time":0.9577372633},
{"learn":[0.8054574306],"iteration":905,"passed_time":9.132152375,"remaining_time":0.947486008},
{"learn":[0.8054256195],"iteration":906,"passed_time":9.140728224,"remaining_time":0.9372521773},
{"learn":[0.8053679003],"iteration":907,"passed_time":9.150028108,"remaining_time":0.927095359},
{"learn":[0.8052939168],"iteration":908,"passed_time":9.157882626,"remaining_time":0.9167957304},
{"learn":[0.8052461178],"iteration":909,"passed_time":9.166519775,"remaining_time":0.9065788789},
{"learn":[0.8051615555],"iteration":910,"passed_time":9.17539903,"remaining_time":0.8963891478},
{"learn":[0.8050784959],"iteration":911,"passed_time":9.185084954,"remaining_time":0.8862801271},
{"learn":[0.8049997515],"iteration":912,"passed_time":9.197508787,"remaining_time":0.8764329293},
{"learn":[0.8049232739],"iteration":913,"passed_time":9.209792056,"remaining_time":0.8665668674},
{"learn":[0.8048412829],"iteration":914,"passed_time":9.218850238,"remaining_time":0.8563959238},
{"learn":[0.8047876683],"iteration":915,"passed_time":9.226415759,"remaining_time":0.8460905282},
{"learn":[0.8047091274],"iteration":916,"passed_time":9.23550392,"remaining_time":0.8359289262},
{"learn":[0.8046295734],"iteration":917,"passed_time":9.242461718,"remaining_time":0.8255793691},
{"learn":[0.8045344962],"iteration":918,"passed_time":9.251614346,"remaining_time":0.8154306442},
{"learn":[0.8044511203],"iteration":919,"passed_time":9.2594516,"remaining_time":0.8051697044},
{"learn":[0.8044113861],"iteration":920,"passed_time":9.268027455,"remaining_time":0.7949773822},
{"learn":[0.8043541164],"iteration":921,"passed_time":9.276086732,"remaining_time":0.7847448645},
{"learn":[0.8043015995],"iteration":922,"passed_time":9.285782989,"remaining_time":0.7746536188},
{"learn":[0.8042310755],"iteration":923,"passed_time":9.296024321,"remaining_time":0.764608061},
{"learn":[0.804146062],"iteration":924,"passed_time":9.304639782,"remaining_time":0.7544302526},
{"learn":[0.8041015566],"iteration":925,"passed_time":9.313215313,"remaining_time":0.7442526276},
{"learn":[0.8040425932],"iteration":926,"passed_time":9.32081235,"remaining_time":0.734001404},
{"learn":[0.8039613979],"iteration":927,"passed_time":9.331181412,"remaining_time":0.7239709716},
{"learn":[0.8038755546],"iteration":928,"passed_time":9.33893013,"remaining_time":0.7137395471},
{"learn":[0.8038020225],"iteration":929,"passed_time":9.34855706,"remaining_time":0.7036548325},
{"learn":[0.80374648],"iteration":930,"passed_time":9.357792544,"remaining_time":0.6935420897},
{"learn":[0.8036831211],"iteration":931,"passed_time":9.366897653,"remaining_time":0.6834217171},
{"learn":[0.8036286255],"iteration":932,"passed_time":9.377793381,"remaining_time":0.6734321077},
{"learn":[0.8035787865],"iteration":933,"passed_time":9.385887087,"remaining_time":0.6632425565},
{"learn":[0.8035163011],"iteration":934,"passed_time":9.395349563,"remaining_time":0.6531526434},
{"learn":[0.8034523806],"iteration":935,"passed_time":9.403052331,"remaining_time":0.6429437491},
{"learn":[0.8033987528],"iteration":936,"passed_time":9.410694086,"remaining_time":0.6327361019},
{"learn":[0.8033021846],"iteration":937,"passed_time":9.41909259,"remaining_time":0.6225839452},
{"learn":[0.8032401542],"iteration":938,"passed_time":9.428762165,"remaining_time":0.6125180959},
{"learn":[0.8031803295],"iteration":939,"passed_time":9.436186195,"remaining_time":0.6023097571},
{"learn":[0.8030974392],"iteration":940,"passed_time":9.445520355,"remaining_time":0.5922270998},
{"learn":[0.8030483045],"iteration":941,"passed_time":9.452790996,"remaining_time":0.5820189785},
{"learn":[0.8029669251],"iteration":942,"passed_time":9.461190632,"remaining_time":0.5718853298},
{"learn":[0.8028960332],"iteration":943,"passed_time":9.468728176,"remaining_time":0.5617042138},
{"learn":[0.8028408604],"iteration":944,"passed_time":9.477987542,"remaining_time":0.5516289046},
{"learn":[0.8027644762],"iteration":945,"passed_time":9.485367671,"remaining_time":0.5414480489},
{"learn":[0.802686409],"iteration":946,"passed_time":9.494508049,"remaining_time":0.5313716226},
{"learn":[0.8026149288],"iteration":947,"passed_time":9.50222203,"remaining_time":0.5212189299},
{"learn":[0.8025357561],"iteration":948,"passed_time":9.511713262,"remaining_time":0.5111668877},
{"learn":[0.8024421605],"iteration":949,"passed_time":9.519334486,"remaining_time":0.5010176045},
{"learn":[0.8023830273],"iteration":950,"passed_time":9.529259542,"remaining_time":0.4909923423},
{"learn":[0.8023351943],"iteration":951,"passed_time":9.537586307,"remaining_time":0.4808867046},
{"learn":[0.8022700339],"iteration":952,"passed_time":9.54543292,"remaining_time":0.4707611199},
{"learn":[0.8021966367],"iteration":953,"passed_time":9.553568696,"remaining_time":0.4606542558},
{"learn":[0.8021657558],"iteration":954,"passed_time":9.561985736,"remaining_time":0.4505647729},
{"learn":[0.8020812392],"iteration":955,"passed_time":9.571622452,"remaining_time":0.4405349246},
{"learn":[0.8020210918],"iteration":956,"passed_time":9.579368741,"remaining_time":0.430420957},
{"learn":[0.8019818208],"iteration":957,"passed_time":9.588490535,"remaining_time":0.4203722364},
{"learn":[0.8019209529],"iteration":958,"passed_time":9.595355837,"remaining_time":0.4102289774},
{"learn":[0.801869285],"iteration":959,"passed_time":9.603471599,"remaining_time":0.40014465},
{"learn":[0.8017923664],"iteration":960,"passed_time":9.611146931,"remaining_time":0.3900465456},
{"learn":[0.8017612686],"iteration":961,"passed_time":9.621259976,"remaining_time":0.3800497704},
{"learn":[0.8017219394],"iteration":962,"passed_time":9.631868539,"remaining_time":0.3700717923},
{"learn":[0.8016493729],"iteration":963,"passed_time":9.642682665,"remaining_time":0.3601001825},
{"learn":[0.8015760553],"iteration":964,"passed_time":9.653941976,"remaining_time":0.3501429732},
{"learn":[0.8015428115],"iteration":965,"passed_time":9.663985094,"remaining_time":0.3401402621},
{"learn":[0.8014662017],"iteration":966,"passed_time":9.675524597,"remaining_time":0.3301885333},
{"learn":[0.8013579077],"iteration":967,"passed_time":9.687178833,"remaining_time":0.3202373168},
{"learn":[0.8012865973],"iteration":968,"passed_time":9.69767272,"remaining_time":0.3102454637},
{"learn":[0.8012231429],"iteration":969,"passed_time":9.709112355,"remaining_time":0.3002818254},
{"learn":[0.8011283456],"iteration":970,"passed_time":9.72666627,"remaining_time":0.2904977568},
{"learn":[0.8010616567],"iteration":971,"passed_time":9.73826989,"remaining_time":0.2805262931},
{"learn":[0.8009835405],"iteration":972,"passed_time":9.748005673,"remaining_time":0.2704996436},
{"learn":[0.8009146212],"iteration":973,"passed_time":9.758697558,"remaining_time":0.2604991135},
{"learn":[0.8008292177],"iteration":974,"passed_time":9.771068045,"remaining_time":0.2505402063},
{"learn":[0.8008035461],"iteration":975,"passed_time":9.781934078,"remaining_time":0.2405393626},
{"learn":[0.8007526756],"iteration":976,"passed_time":9.790965953,"remaining_time":0.230493569},
{"learn":[0.8006703836],"iteration":977,"passed_time":9.801511623,"remaining_time":0.2204839015},
{"learn":[0.8006150564],"iteration":978,"passed_time":9.812909471,"remaining_time":0.2104914187},
{"learn":[0.8005487521],"iteration":979,"passed_time":9.822924499,"remaining_time":0.2004678469},
{"learn":[0.8005032781],"iteration":980,"passed_time":9.835789522,"remaining_time":0.1904994912},
{"learn":[0.8004345766],"iteration":981,"passed_time":9.847204467,"remaining_time":0.1804986562},
{"learn":[0.8003314197],"iteration":982,"passed_time":9.857272614,"remaining_time":0.1704716525},
{"learn":[0.8002633834],"iteration":983,"passed_time":9.86955453,"remaining_time":0.1604805615},
{"learn":[0.8002326646],"iteration":984,"passed_time":9.88140444,"remaining_time":0.1504782402},
{"learn":[0.800090268],"iteration":985,"passed_time":9.892288404,"remaining_time":0.140458456},
{"learn":[0.8000194431],"iteration":986,"passed_time":9.901940764,"remaining_time":0.130420699},
{"learn":[0.7999282822],"iteration":987,"passed_time":9.91448652,"remaining_time":0.1204188646},
{"learn":[0.7998683797],"iteration":988,"passed_time":9.925768769,"remaining_time":0.1103978326},
{"learn":[0.7998275461],"iteration":989,"passed_time":9.935313667,"remaining_time":0.1003567037},
{"learn":[0.7998095936],"iteration":990,"passed_time":9.944997062,"remaining_time":0.09031783406},
{"learn":[0.7997398166],"iteration":991,"passed_time":9.956177857,"remaining_time":0.08029175691},
{"learn":[0.7996314671],"iteration":992,"passed_time":9.968157677,"remaining_time":0.07026898664},
{"learn":[0.7995715647],"iteration":993,"passed_time":9.979375253,"remaining_time":0.06023767758},
{"learn":[0.7995037788],"iteration":994,"passed_time":9.989174444,"remaining_time":0.0501968565},
{"learn":[0.7994391156],"iteration":995,"passed_time":9.998987776,"remaining_time":0.04015657741},
{"learn":[0.7993688888],"iteration":996,"passed_time":10.01083727,"remaining_time":0.03012288046},
{"learn":[0.7993016968],"iteration":997,"passed_time":10.02290696,"remaining_time":0.02008598589},
{"learn":[0.7992117492],"iteration":998,"passed_time":10.03332202,"remaining_time":0.01004336538},
{"learn":[0.7991449592],"iteration":999,"passed_time":10.04599255,"remaining_time":0}
]}